{"status":"success","result":"{\"stage\":{\"x_coord\":631,\"y_coord\":773,\"width\":269,\"height\":12,\"position\":\"bottom\"},\"levels\":[{\"id\":1,\"name\":\"Партер\",\"seats\":[{\"place\":\"22\",\"row\":\"1\",\"x_coord\":420,\"y_coord\":697,\"linked_seats\":[]},{\"place\":\"21\",\"row\":\"1\",\"x_coord\":440,\"y_coord\":697,\"linked_seats\":[]},{\"place\":\"20\",\"row\":\"1\",\"x_coord\":460,\"y_coord\":697,\"linked_seats\":[]},{\"place\":\"19\",\"row\":\"1\",\"x_coord\":480,\"y_coord\":697,\"linked_seats\":[]},{\"place\":\"18\",\"row\":\"1\",\"x_coord\":500,\"y_coord\":697,\"linked_seats\":[]},{\"place\":\"17\",\"row\":\"1\",\"x_coord\":520,\"y_coord\":697,\"linked_seats\":[]},{\"place\":\"16\",\"row\":\"1\",\"x_coord\":540,\"y_coord\":697,\"linked_seats\":[]},{\"place\":\"15\",\"row\":\"1\",\"x_coord\":560,\"y_coord\":697,\"linked_seats\":[]},{\"place\":\"14\",\"row\":\"1\",\"x_coord\":580,\"y_coord\":697,\"linked_seats\":[]},{\"place\":\"13\",\"row\":\"1\",\"x_coord\":600,\"y_coord\":697,\"linked_seats\":[]},{\"place\":\"12\",\"row\":\"1\",\"x_coord\":620,\"y_coord\":697,\"linked_seats\":[]},{\"place\":\"11\",\"row\":\"1\",\"x_coord\":640,\"y_coord\":697,\"linked_seats\":[]},{\"place\":\"10\",\"row\":\"1\",\"x_coord\":660,\"y_coord\":697,\"linked_seats\":[]},{\"place\":\"9\",\"row\":\"1\",\"x_coord\":680,\"y_coord\":697,\"linked_seats\":[]},{\"place\":\"8\",\"row\":\"1\",\"x_coord\":700,\"y_coord\":697,\"linked_seats\":[]},{\"place\":\"7\",\"row\":\"1\",\"x_coord\":720,\"y_coord\":697,\"linked_seats\":[]},{\"place\":\"6\",\"row\":\"1\",\"x_coord\":740,\"y_coord\":697,\"linked_seats\":[]},{\"place\":\"5\",\"row\":\"1\",\"x_coord\":760,\"y_coord\":697,\"linked_seats\":[]},{\"place\":\"4\",\"row\":\"1\",\"x_coord\":780,\"y_coord\":697,\"linked_seats\":[]},{\"place\":\"3\",\"row\":\"1\",\"x_coord\":800,\"y_coord\":697,\"linked_seats\":[]},{\"place\":\"2\",\"row\":\"1\",\"x_coord\":820,\"y_coord\":697,\"linked_seats\":[]},{\"place\":\"1\",\"row\":\"1\",\"x_coord\":840,\"y_coord\":697,\"linked_seats\":[]},{\"place\":\"23\",\"row\":\"2\",\"x_coord\":410,\"y_coord\":675,\"linked_seats\":[]},{\"place\":\"22\",\"row\":\"2\",\"x_coord\":430,\"y_coord\":675,\"linked_seats\":[]},{\"place\":\"21\",\"row\":\"2\",\"x_coord\":450,\"y_coord\":675,\"linked_seats\":[]},{\"place\":\"20\",\"row\":\"2\",\"x_coord\":470,\"y_coord\":675,\"linked_seats\":[]},{\"place\":\"19\",\"row\":\"2\",\"x_coord\":490,\"y_coord\":675,\"linked_seats\":[]},{\"place\":\"18\",\"row\":\"2\",\"x_coord\":510,\"y_coord\":675,\"linked_seats\":[]},{\"place\":\"17\",\"row\":\"2\",\"x_coord\":530,\"y_coord\":675,\"linked_seats\":[]},{\"place\":\"16\",\"row\":\"2\",\"x_coord\":550,\"y_coord\":675,\"linked_seats\":[]},{\"place\":\"15\",\"row\":\"2\",\"x_coord\":570,\"y_coord\":675,\"linked_seats\":[]},{\"place\":\"14\",\"row\":\"2\",\"x_coord\":590,\"y_coord\":675,\"linked_seats\":[]},{\"place\":\"13\",\"row\":\"2\",\"x_coord\":610,\"y_coord\":675,\"linked_seats\":[]},{\"place\":\"12\",\"row\":\"2\",\"x_coord\":630,\"y_coord\":675,\"linked_seats\":[]},{\"place\":\"11\",\"row\":\"2\",\"x_coord\":650,\"y_coord\":675,\"linked_seats\":[]},{\"place\":\"10\",\"row\":\"2\",\"x_coord\":670,\"y_coord\":675,\"linked_seats\":[]},{\"place\":\"9\",\"row\":\"2\",\"x_coord\":690,\"y_coord\":675,\"linked_seats\":[]},{\"place\":\"8\",\"row\":\"2\",\"x_coord\":710,\"y_coord\":675,\"linked_seats\":[]},{\"place\":\"7\",\"row\":\"2\",\"x_coord\":730,\"y_coord\":675,\"linked_seats\":[]},{\"place\":\"6\",\"row\":\"2\",\"x_coord\":750,\"y_coord\":675,\"linked_seats\":[]},{\"place\":\"5\",\"row\":\"2\",\"x_coord\":770,\"y_coord\":675,\"linked_seats\":[]},{\"place\":\"4\",\"row\":\"2\",\"x_coord\":790,\"y_coord\":675,\"linked_seats\":[]},{\"place\":\"3\",\"row\":\"2\",\"x_coord\":810,\"y_coord\":675,\"linked_seats\":[]},{\"place\":\"2\",\"row\":\"2\",\"x_coord\":830,\"y_coord\":675,\"linked_seats\":[]},{\"place\":\"1\",\"row\":\"2\",\"x_coord\":850,\"y_coord\":675,\"linked_seats\":[]},{\"place\":\"24\",\"row\":\"3\",\"x_coord\":400,\"y_coord\":653,\"linked_seats\":[]},{\"place\":\"23\",\"row\":\"3\",\"x_coord\":420,\"y_coord\":653,\"linked_seats\":[]},{\"place\":\"22\",\"row\":\"3\",\"x_coord\":440,\"y_coord\":653,\"linked_seats\":[]},{\"place\":\"21\",\"row\":\"3\",\"x_coord\":460,\"y_coord\":653,\"linked_seats\":[]},{\"place\":\"20\",\"row\":\"3\",\"x_coord\":480,\"y_coord\":653,\"linked_seats\":[]},{\"place\":\"19\",\"row\":\"3\",\"x_coord\":500,\"y_coord\":653,\"linked_seats\":[]},{\"place\":\"18\",\"row\":\"3\",\"x_coord\":520,\"y_coord\":653,\"linked_seats\":[]},{\"place\":\"17\",\"row\":\"3\",\"x_coord\":540,\"y_coord\":653,\"linked_seats\":[]},{\"place\":\"16\",\"row\":\"3\",\"x_coord\":560,\"y_coord\":653,\"linked_seats\":[]},{\"place\":\"15\",\"row\":\"3\",\"x_coord\":580,\"y_coord\":653,\"linked_seats\":[]},{\"place\":\"14\",\"row\":\"3\",\"x_coord\":600,\"y_coord\":653,\"linked_seats\":[]},{\"place\":\"13\",\"row\":\"3\",\"x_coord\":620,\"y_coord\":653,\"linked_seats\":[]},{\"place\":\"12\",\"row\":\"3\",\"x_coord\":640,\"y_coord\":653,\"linked_seats\":[]},{\"place\":\"11\",\"row\":\"3\",\"x_coord\":660,\"y_coord\":653,\"linked_seats\":[]},{\"place\":\"10\",\"row\":\"3\",\"x_coord\":680,\"y_coord\":653,\"linked_seats\":[]},{\"place\":\"9\",\"row\":\"3\",\"x_coord\":700,\"y_coord\":653,\"linked_seats\":[]},{\"place\":\"8\",\"row\":\"3\",\"x_coord\":720,\"y_coord\":653,\"linked_seats\":[]},{\"place\":\"7\",\"row\":\"3\",\"x_coord\":740,\"y_coord\":653,\"linked_seats\":[]},{\"place\":\"6\",\"row\":\"3\",\"x_coord\":760,\"y_coord\":653,\"linked_seats\":[]},{\"place\":\"5\",\"row\":\"3\",\"x_coord\":780,\"y_coord\":653,\"linked_seats\":[]},{\"place\":\"4\",\"row\":\"3\",\"x_coord\":800,\"y_coord\":653,\"linked_seats\":[]},{\"place\":\"3\",\"row\":\"3\",\"x_coord\":820,\"y_coord\":653,\"linked_seats\":[]},{\"place\":\"2\",\"row\":\"3\",\"x_coord\":840,\"y_coord\":653,\"linked_seats\":[]},{\"place\":\"1\",\"row\":\"3\",\"x_coord\":860,\"y_coord\":653,\"linked_seats\":[]},{\"place\":\"25\",\"row\":\"4\",\"x_coord\":390,\"y_coord\":631,\"linked_seats\":[]},{\"place\":\"24\",\"row\":\"4\",\"x_coord\":410,\"y_coord\":631,\"linked_seats\":[]},{\"place\":\"23\",\"row\":\"4\",\"x_coord\":430,\"y_coord\":631,\"linked_seats\":[]},{\"place\":\"22\",\"row\":\"4\",\"x_coord\":450,\"y_coord\":631,\"linked_seats\":[]},{\"place\":\"21\",\"row\":\"4\",\"x_coord\":470,\"y_coord\":631,\"linked_seats\":[]},{\"place\":\"20\",\"row\":\"4\",\"x_coord\":490,\"y_coord\":631,\"linked_seats\":[]},{\"place\":\"19\",\"row\":\"4\",\"x_coord\":510,\"y_coord\":631,\"linked_seats\":[]},{\"place\":\"18\",\"row\":\"4\",\"x_coord\":530,\"y_coord\":631,\"linked_seats\":[]},{\"place\":\"17\",\"row\":\"4\",\"x_coord\":550,\"y_coord\":631,\"linked_seats\":[]},{\"place\":\"16\",\"row\":\"4\",\"x_coord\":570,\"y_coord\":631,\"linked_seats\":[]},{\"place\":\"15\",\"row\":\"4\",\"x_coord\":590,\"y_coord\":631,\"linked_seats\":[]},{\"place\":\"14\",\"row\":\"4\",\"x_coord\":610,\"y_coord\":631,\"linked_seats\":[]},{\"place\":\"13\",\"row\":\"4\",\"x_coord\":630,\"y_coord\":631,\"linked_seats\":[]},{\"place\":\"12\",\"row\":\"4\",\"x_coord\":650,\"y_coord\":631,\"linked_seats\":[]},{\"place\":\"11\",\"row\":\"4\",\"x_coord\":670,\"y_coord\":631,\"linked_seats\":[]},{\"place\":\"10\",\"row\":\"4\",\"x_coord\":690,\"y_coord\":631,\"linked_seats\":[]},{\"place\":\"9\",\"row\":\"4\",\"x_coord\":710,\"y_coord\":631,\"linked_seats\":[]},{\"place\":\"8\",\"row\":\"4\",\"x_coord\":730,\"y_coord\":631,\"linked_seats\":[]},{\"place\":\"7\",\"row\":\"4\",\"x_coord\":750,\"y_coord\":631,\"linked_seats\":[]},{\"place\":\"6\",\"row\":\"4\",\"x_coord\":770,\"y_coord\":631,\"linked_seats\":[]},{\"place\":\"5\",\"row\":\"4\",\"x_coord\":790,\"y_coord\":631,\"linked_seats\":[]},{\"place\":\"4\",\"row\":\"4\",\"x_coord\":810,\"y_coord\":631,\"linked_seats\":[]},{\"place\":\"3\",\"row\":\"4\",\"x_coord\":830,\"y_coord\":631,\"linked_seats\":[]},{\"place\":\"2\",\"row\":\"4\",\"x_coord\":850,\"y_coord\":631,\"linked_seats\":[]},{\"place\":\"1\",\"row\":\"4\",\"x_coord\":870,\"y_coord\":631,\"linked_seats\":[]},{\"place\":\"25\",\"row\":\"5\",\"x_coord\":390,\"y_coord\":609,\"linked_seats\":[]},{\"place\":\"24\",\"row\":\"5\",\"x_coord\":410,\"y_coord\":609,\"linked_seats\":[]},{\"place\":\"23\",\"row\":\"5\",\"x_coord\":430,\"y_coord\":609,\"linked_seats\":[]},{\"place\":\"22\",\"row\":\"5\",\"x_coord\":450,\"y_coord\":609,\"linked_seats\":[]},{\"place\":\"21\",\"row\":\"5\",\"x_coord\":470,\"y_coord\":609,\"linked_seats\":[]},{\"place\":\"20\",\"row\":\"5\",\"x_coord\":490,\"y_coord\":609,\"linked_seats\":[]},{\"place\":\"19\",\"row\":\"5\",\"x_coord\":510,\"y_coord\":609,\"linked_seats\":[]},{\"place\":\"18\",\"row\":\"5\",\"x_coord\":530,\"y_coord\":609,\"linked_seats\":[]},{\"place\":\"17\",\"row\":\"5\",\"x_coord\":550,\"y_coord\":609,\"linked_seats\":[]},{\"place\":\"16\",\"row\":\"5\",\"x_coord\":570,\"y_coord\":609,\"linked_seats\":[]},{\"place\":\"15\",\"row\":\"5\",\"x_coord\":590,\"y_coord\":609,\"linked_seats\":[]},{\"place\":\"14\",\"row\":\"5\",\"x_coord\":610,\"y_coord\":609,\"linked_seats\":[]},{\"place\":\"13\",\"row\":\"5\",\"x_coord\":630,\"y_coord\":609,\"linked_seats\":[]},{\"place\":\"12\",\"row\":\"5\",\"x_coord\":650,\"y_coord\":609,\"linked_seats\":[]},{\"place\":\"11\",\"row\":\"5\",\"x_coord\":670,\"y_coord\":609,\"linked_seats\":[]},{\"place\":\"10\",\"row\":\"5\",\"x_coord\":690,\"y_coord\":609,\"linked_seats\":[]},{\"place\":\"9\",\"row\":\"5\",\"x_coord\":710,\"y_coord\":609,\"linked_seats\":[]},{\"place\":\"8\",\"row\":\"5\",\"x_coord\":730,\"y_coord\":609,\"linked_seats\":[]},{\"place\":\"7\",\"row\":\"5\",\"x_coord\":750,\"y_coord\":609,\"linked_seats\":[]},{\"place\":\"6\",\"row\":\"5\",\"x_coord\":770,\"y_coord\":609,\"linked_seats\":[]},{\"place\":\"5\",\"row\":\"5\",\"x_coord\":790,\"y_coord\":609,\"linked_seats\":[]},{\"place\":\"4\",\"row\":\"5\",\"x_coord\":810,\"y_coord\":609,\"linked_seats\":[]},{\"place\":\"3\",\"row\":\"5\",\"x_coord\":830,\"y_coord\":609,\"linked_seats\":[]},{\"place\":\"2\",\"row\":\"5\",\"x_coord\":850,\"y_coord\":609,\"linked_seats\":[]},{\"place\":\"1\",\"row\":\"5\",\"x_coord\":870,\"y_coord\":609,\"linked_seats\":[]},{\"place\":\"24\",\"row\":\"6\",\"x_coord\":400,\"y_coord\":587,\"linked_seats\":[]},{\"place\":\"23\",\"row\":\"6\",\"x_coord\":420,\"y_coord\":587,\"linked_seats\":[]},{\"place\":\"22\",\"row\":\"6\",\"x_coord\":440,\"y_coord\":587,\"linked_seats\":[]},{\"place\":\"21\",\"row\":\"6\",\"x_coord\":460,\"y_coord\":587,\"linked_seats\":[]},{\"place\":\"20\",\"row\":\"6\",\"x_coord\":480,\"y_coord\":587,\"linked_seats\":[]},{\"place\":\"19\",\"row\":\"6\",\"x_coord\":500,\"y_coord\":587,\"linked_seats\":[]},{\"place\":\"18\",\"row\":\"6\",\"x_coord\":520,\"y_coord\":587,\"linked_seats\":[]},{\"place\":\"17\",\"row\":\"6\",\"x_coord\":540,\"y_coord\":587,\"linked_seats\":[]},{\"place\":\"16\",\"row\":\"6\",\"x_coord\":560,\"y_coord\":587,\"linked_seats\":[]},{\"place\":\"15\",\"row\":\"6\",\"x_coord\":580,\"y_coord\":587,\"linked_seats\":[]},{\"place\":\"14\",\"row\":\"6\",\"x_coord\":600,\"y_coord\":587,\"linked_seats\":[]},{\"place\":\"13\",\"row\":\"6\",\"x_coord\":620,\"y_coord\":587,\"linked_seats\":[]},{\"place\":\"12\",\"row\":\"6\",\"x_coord\":640,\"y_coord\":587,\"linked_seats\":[]},{\"place\":\"11\",\"row\":\"6\",\"x_coord\":660,\"y_coord\":587,\"linked_seats\":[]},{\"place\":\"10\",\"row\":\"6\",\"x_coord\":680,\"y_coord\":587,\"linked_seats\":[]},{\"place\":\"9\",\"row\":\"6\",\"x_coord\":700,\"y_coord\":587,\"linked_seats\":[]},{\"place\":\"8\",\"row\":\"6\",\"x_coord\":720,\"y_coord\":587,\"linked_seats\":[]},{\"place\":\"7\",\"row\":\"6\",\"x_coord\":740,\"y_coord\":587,\"linked_seats\":[]},{\"place\":\"6\",\"row\":\"6\",\"x_coord\":760,\"y_coord\":587,\"linked_seats\":[]},{\"place\":\"5\",\"row\":\"6\",\"x_coord\":780,\"y_coord\":587,\"linked_seats\":[]},{\"place\":\"4\",\"row\":\"6\",\"x_coord\":800,\"y_coord\":587,\"linked_seats\":[]},{\"place\":\"3\",\"row\":\"6\",\"x_coord\":820,\"y_coord\":587,\"linked_seats\":[]},{\"place\":\"2\",\"row\":\"6\",\"x_coord\":840,\"y_coord\":587,\"linked_seats\":[]},{\"place\":\"1\",\"row\":\"6\",\"x_coord\":860,\"y_coord\":587,\"linked_seats\":[]},{\"place\":\"24\",\"row\":\"7\",\"x_coord\":400,\"y_coord\":565,\"linked_seats\":[]},{\"place\":\"23\",\"row\":\"7\",\"x_coord\":420,\"y_coord\":565,\"linked_seats\":[]},{\"place\":\"22\",\"row\":\"7\",\"x_coord\":440,\"y_coord\":565,\"linked_seats\":[]},{\"place\":\"21\",\"row\":\"7\",\"x_coord\":460,\"y_coord\":565,\"linked_seats\":[]},{\"place\":\"20\",\"row\":\"7\",\"x_coord\":480,\"y_coord\":565,\"linked_seats\":[]},{\"place\":\"19\",\"row\":\"7\",\"x_coord\":500,\"y_coord\":565,\"linked_seats\":[]},{\"place\":\"18\",\"row\":\"7\",\"x_coord\":520,\"y_coord\":565,\"linked_seats\":[]},{\"place\":\"17\",\"row\":\"7\",\"x_coord\":540,\"y_coord\":565,\"linked_seats\":[]},{\"place\":\"16\",\"row\":\"7\",\"x_coord\":560,\"y_coord\":565,\"linked_seats\":[]},{\"place\":\"15\",\"row\":\"7\",\"x_coord\":580,\"y_coord\":565,\"linked_seats\":[]},{\"place\":\"14\",\"row\":\"7\",\"x_coord\":600,\"y_coord\":565,\"linked_seats\":[]},{\"place\":\"13\",\"row\":\"7\",\"x_coord\":620,\"y_coord\":565,\"linked_seats\":[]},{\"place\":\"12\",\"row\":\"7\",\"x_coord\":640,\"y_coord\":565,\"linked_seats\":[]},{\"place\":\"11\",\"row\":\"7\",\"x_coord\":660,\"y_coord\":565,\"linked_seats\":[]},{\"place\":\"10\",\"row\":\"7\",\"x_coord\":680,\"y_coord\":565,\"linked_seats\":[]},{\"place\":\"9\",\"row\":\"7\",\"x_coord\":700,\"y_coord\":565,\"linked_seats\":[]},{\"place\":\"8\",\"row\":\"7\",\"x_coord\":720,\"y_coord\":565,\"linked_seats\":[]},{\"place\":\"7\",\"row\":\"7\",\"x_coord\":740,\"y_coord\":565,\"linked_seats\":[]},{\"place\":\"6\",\"row\":\"7\",\"x_coord\":760,\"y_coord\":565,\"linked_seats\":[]},{\"place\":\"5\",\"row\":\"7\",\"x_coord\":780,\"y_coord\":565,\"linked_seats\":[]},{\"place\":\"4\",\"row\":\"7\",\"x_coord\":800,\"y_coord\":565,\"linked_seats\":[]},{\"place\":\"3\",\"row\":\"7\",\"x_coord\":820,\"y_coord\":565,\"linked_seats\":[]},{\"place\":\"2\",\"row\":\"7\",\"x_coord\":840,\"y_coord\":565,\"linked_seats\":[]},{\"place\":\"1\",\"row\":\"7\",\"x_coord\":860,\"y_coord\":565,\"linked_seats\":[]},{\"place\":\"20\",\"row\":\"8\",\"x_coord\":440,\"y_coord\":543,\"linked_seats\":[]},{\"place\":\"19\",\"row\":\"8\",\"x_coord\":460,\"y_coord\":543,\"linked_seats\":[]},{\"place\":\"18\",\"row\":\"8\",\"x_coord\":480,\"y_coord\":543,\"linked_seats\":[]},{\"place\":\"17\",\"row\":\"8\",\"x_coord\":500,\"y_coord\":543,\"linked_seats\":[]},{\"place\":\"16\",\"row\":\"8\",\"x_coord\":520,\"y_coord\":543,\"linked_seats\":[]},{\"place\":\"15\",\"row\":\"8\",\"x_coord\":540,\"y_coord\":543,\"linked_seats\":[]},{\"place\":\"14\",\"row\":\"8\",\"x_coord\":560,\"y_coord\":543,\"linked_seats\":[]},{\"place\":\"13\",\"row\":\"8\",\"x_coord\":580,\"y_coord\":543,\"linked_seats\":[]},{\"place\":\"8\",\"row\":\"8\",\"x_coord\":680,\"y_coord\":543,\"linked_seats\":[]},{\"place\":\"7\",\"row\":\"8\",\"x_coord\":700,\"y_coord\":543,\"linked_seats\":[]},{\"place\":\"6\",\"row\":\"8\",\"x_coord\":720,\"y_coord\":543,\"linked_seats\":[]},{\"place\":\"5\",\"row\":\"8\",\"x_coord\":740,\"y_coord\":543,\"linked_seats\":[]},{\"place\":\"4\",\"row\":\"8\",\"x_coord\":760,\"y_coord\":543,\"linked_seats\":[]},{\"place\":\"3\",\"row\":\"8\",\"x_coord\":780,\"y_coord\":543,\"linked_seats\":[]},{\"place\":\"2\",\"row\":\"8\",\"x_coord\":800,\"y_coord\":543,\"linked_seats\":[]},{\"place\":\"1\",\"row\":\"8\",\"x_coord\":820,\"y_coord\":543,\"linked_seats\":[]},{\"place\":\"15\",\"row\":\"9\",\"x_coord\":490,\"y_coord\":521,\"linked_seats\":[]},{\"place\":\"14\",\"row\":\"9\",\"x_coord\":510,\"y_coord\":521,\"linked_seats\":[]},{\"place\":\"13\",\"row\":\"9\",\"x_coord\":530,\"y_coord\":521,\"linked_seats\":[]},{\"place\":\"12\",\"row\":\"9\",\"x_coord\":550,\"y_coord\":521,\"linked_seats\":[]},{\"place\":\"11\",\"row\":\"9\",\"x_coord\":570,\"y_coord\":521,\"linked_seats\":[]},{\"place\":\"10\",\"row\":\"9\",\"x_coord\":590,\"y_coord\":521,\"linked_seats\":[]},{\"place\":\"9\",\"row\":\"9\",\"x_coord\":610,\"y_coord\":521,\"linked_seats\":[]},{\"place\":\"8\",\"row\":\"9\",\"x_coord\":630,\"y_coord\":521,\"linked_seats\":[]},{\"place\":\"7\",\"row\":\"9\",\"x_coord\":650,\"y_coord\":521,\"linked_seats\":[]},{\"place\":\"6\",\"row\":\"9\",\"x_coord\":670,\"y_coord\":521,\"linked_seats\":[]},{\"place\":\"5\",\"row\":\"9\",\"x_coord\":690,\"y_coord\":521,\"linked_seats\":[]},{\"place\":\"4\",\"row\":\"9\",\"x_coord\":710,\"y_coord\":521,\"linked_seats\":[]},{\"place\":\"3\",\"row\":\"9\",\"x_coord\":730,\"y_coord\":521,\"linked_seats\":[]},{\"place\":\"2\",\"row\":\"9\",\"x_coord\":750,\"y_coord\":521,\"linked_seats\":[]},{\"place\":\"1\",\"row\":\"9\",\"x_coord\":770,\"y_coord\":521,\"linked_seats\":[]}],\"outline\":\" M340.99434089660645 735.0 C334.37004947662354 735.0 329.0 729.6274108886719 329.0 723.0 L329.0 567.2353591918945 C329.0 563.3211288452148 330.90814554691315 559.6528930664062 334.11248254776 557.4070663452148 C344.5383005142212 550.0999221801758 352.5077896118164 544.6451110839844 358.0209503173828 541.0426330566406 C436.45448303222656 489.79164123535156 530.1638336181641 460.0 630.8265991210938 460.0 C724.8495483398438 460.0 812.8058166503906 485.9910945892334 887.9141845703125 531.1834411621094 C896.9022827148438 536.5915298461914 909.5557861328125 544.998405456543 925.8746948242188 556.4040679931641 C929.0864868164062 558.6488800048828 931.0 562.3215789794922 931.0 566.2413482666016 L931.0 723.0 C931.0 729.6274108886719 925.6299438476562 735.0 919.0056762695312 735.0 L340.99434089660645 735.0 Z\",\"sections\":[],\"admission\":false},{\"id\":2,\"name\":\"Амфитеатр\",\"seats\":[{\"place\":\"1\",\"row\":\"1\",\"x_coord\":1018,\"y_coord\":587,\"linked_seats\":[]},{\"place\":\"2\",\"row\":\"1\",\"x_coord\":1003,\"y_coord\":573,\"linked_seats\":[]},{\"place\":\"3\",\"row\":\"1\",\"x_coord\":989,\"y_coord\":559,\"linked_seats\":[]},{\"place\":\"4\",\"row\":\"1\",\"x_coord\":973,\"y_coord\":546,\"linked_seats\":[]},{\"place\":\"5\",\"row\":\"1\",\"x_coord\":957,\"y_coord\":533,\"linked_seats\":[]},{\"place\":\"6\",\"row\":\"1\",\"x_coord\":941,\"y_coord\":521,\"linked_seats\":[]},{\"place\":\"7\",\"row\":\"1\",\"x_coord\":925,\"y_coord\":510,\"linked_seats\":[]},{\"place\":\"8\",\"row\":\"1\",\"x_coord\":907,\"y_coord\":499,\"linked_seats\":[]},{\"place\":\"9\",\"row\":\"1\",\"x_coord\":890,\"y_coord\":489,\"linked_seats\":[]},{\"place\":\"10\",\"row\":\"1\",\"x_coord\":872,\"y_coord\":480,\"linked_seats\":[]},{\"place\":\"11\",\"row\":\"1\",\"x_coord\":854,\"y_coord\":471,\"linked_seats\":[]},{\"place\":\"30\",\"row\":\"1\",\"x_coord\":408,\"y_coord\":471,\"linked_seats\":[]},{\"place\":\"31\",\"row\":\"1\",\"x_coord\":389,\"y_coord\":480,\"linked_seats\":[]},{\"place\":\"32\",\"row\":\"1\",\"x_coord\":372,\"y_coord\":489,\"linked_seats\":[]},{\"place\":\"33\",\"row\":\"1\",\"x_coord\":354,\"y_coord\":499,\"linked_seats\":[]},{\"place\":\"34\",\"row\":\"1\",\"x_coord\":337,\"y_coord\":510,\"linked_seats\":[]},{\"place\":\"35\",\"row\":\"1\",\"x_coord\":320,\"y_coord\":521,\"linked_seats\":[]},{\"place\":\"36\",\"row\":\"1\",\"x_coord\":304,\"y_coord\":533,\"linked_seats\":[]},{\"place\":\"37\",\"row\":\"1\",\"x_coord\":288,\"y_coord\":546,\"linked_seats\":[]},{\"place\":\"38\",\"row\":\"1\",\"x_coord\":273,\"y_coord\":559,\"linked_seats\":[]},{\"place\":\"39\",\"row\":\"1\",\"x_coord\":258,\"y_coord\":573,\"linked_seats\":[]},{\"place\":\"40\",\"row\":\"1\",\"x_coord\":244,\"y_coord\":587,\"linked_seats\":[]},{\"place\":\"1\",\"row\":\"2\",\"x_coord\":1026,\"y_coord\":564,\"linked_seats\":[]},{\"place\":\"2\",\"row\":\"2\",\"x_coord\":1012,\"y_coord\":550,\"linked_seats\":[]},{\"place\":\"3\",\"row\":\"2\",\"x_coord\":997,\"y_coord\":537,\"linked_seats\":[]},{\"place\":\"4\",\"row\":\"2\",\"x_coord\":981,\"y_coord\":524,\"linked_seats\":[]},{\"place\":\"5\",\"row\":\"2\",\"x_coord\":965,\"y_coord\":511,\"linked_seats\":[]},{\"place\":\"6\",\"row\":\"2\",\"x_coord\":949,\"y_coord\":500,\"linked_seats\":[]},{\"place\":\"7\",\"row\":\"2\",\"x_coord\":932,\"y_coord\":489,\"linked_seats\":[]},{\"place\":\"8\",\"row\":\"2\",\"x_coord\":915,\"y_coord\":478,\"linked_seats\":[]},{\"place\":\"9\",\"row\":\"2\",\"x_coord\":897,\"y_coord\":468,\"linked_seats\":[]},{\"place\":\"10\",\"row\":\"2\",\"x_coord\":880,\"y_coord\":459,\"linked_seats\":[]},{\"place\":\"11\",\"row\":\"2\",\"x_coord\":861,\"y_coord\":450,\"linked_seats\":[]},{\"place\":\"12\",\"row\":\"2\",\"x_coord\":843,\"y_coord\":442,\"linked_seats\":[]},{\"place\":\"13\",\"row\":\"2\",\"x_coord\":824,\"y_coord\":435,\"linked_seats\":[]},{\"place\":\"14\",\"row\":\"2\",\"x_coord\":768,\"y_coord\":418,\"linked_seats\":[]},{\"place\":\"15\",\"row\":\"2\",\"x_coord\":749,\"y_coord\":413,\"linked_seats\":[]},{\"place\":\"16\",\"row\":\"2\",\"x_coord\":730,\"y_coord\":409,\"linked_seats\":[]},{\"place\":\"17\",\"row\":\"2\",\"x_coord\":710,\"y_coord\":406,\"linked_seats\":[]},{\"place\":\"18\",\"row\":\"2\",\"x_coord\":690,\"y_coord\":404,\"linked_seats\":[]},{\"place\":\"19\",\"row\":\"2\",\"x_coord\":671,\"y_coord\":402,\"linked_seats\":[]},{\"place\":\"20\",\"row\":\"2\",\"x_coord\":651,\"y_coord\":401,\"linked_seats\":[]},{\"place\":\"21\",\"row\":\"2\",\"x_coord\":631,\"y_coord\":401,\"linked_seats\":[]},{\"place\":\"22\",\"row\":\"2\",\"x_coord\":611,\"y_coord\":401,\"linked_seats\":[]},{\"place\":\"23\",\"row\":\"2\",\"x_coord\":592,\"y_coord\":402,\"linked_seats\":[]},{\"place\":\"24\",\"row\":\"2\",\"x_coord\":572,\"y_coord\":404,\"linked_seats\":[]},{\"place\":\"25\",\"row\":\"2\",\"x_coord\":552,\"y_coord\":406,\"linked_seats\":[]},{\"place\":\"26\",\"row\":\"2\",\"x_coord\":533,\"y_coord\":409,\"linked_seats\":[]},{\"place\":\"27\",\"row\":\"2\",\"x_coord\":513,\"y_coord\":413,\"linked_seats\":[]},{\"place\":\"28\",\"row\":\"2\",\"x_coord\":494,\"y_coord\":417,\"linked_seats\":[]},{\"place\":\"29\",\"row\":\"2\",\"x_coord\":438,\"y_coord\":435,\"linked_seats\":[]},{\"place\":\"30\",\"row\":\"2\",\"x_coord\":420,\"y_coord\":442,\"linked_seats\":[]},{\"place\":\"31\",\"row\":\"2\",\"x_coord\":401,\"y_coord\":450,\"linked_seats\":[]},{\"place\":\"32\",\"row\":\"2\",\"x_coord\":383,\"y_coord\":458,\"linked_seats\":[]},{\"place\":\"33\",\"row\":\"2\",\"x_coord\":365,\"y_coord\":468,\"linked_seats\":[]},{\"place\":\"34\",\"row\":\"2\",\"x_coord\":347,\"y_coord\":478,\"linked_seats\":[]},{\"place\":\"35\",\"row\":\"2\",\"x_coord\":330,\"y_coord\":488,\"linked_seats\":[]},{\"place\":\"36\",\"row\":\"2\",\"x_coord\":313,\"y_coord\":499,\"linked_seats\":[]},{\"place\":\"37\",\"row\":\"2\",\"x_coord\":297,\"y_coord\":511,\"linked_seats\":[]},{\"place\":\"38\",\"row\":\"2\",\"x_coord\":281,\"y_coord\":523,\"linked_seats\":[]},{\"place\":\"39\",\"row\":\"2\",\"x_coord\":265,\"y_coord\":536,\"linked_seats\":[]},{\"place\":\"40\",\"row\":\"2\",\"x_coord\":250,\"y_coord\":550,\"linked_seats\":[]},{\"place\":\"41\",\"row\":\"2\",\"x_coord\":236,\"y_coord\":564,\"linked_seats\":[]},{\"place\":\"1\",\"row\":\"3\",\"x_coord\":1034,\"y_coord\":541,\"linked_seats\":[]},{\"place\":\"2\",\"row\":\"3\",\"x_coord\":1019,\"y_coord\":527,\"linked_seats\":[]},{\"place\":\"3\",\"row\":\"3\",\"x_coord\":1004,\"y_coord\":514,\"linked_seats\":[]},{\"place\":\"4\",\"row\":\"3\",\"x_coord\":988,\"y_coord\":502,\"linked_seats\":[]},{\"place\":\"5\",\"row\":\"3\",\"x_coord\":972,\"y_coord\":489,\"linked_seats\":[]},{\"place\":\"6\",\"row\":\"3\",\"x_coord\":956,\"y_coord\":478,\"linked_seats\":[]},{\"place\":\"7\",\"row\":\"3\",\"x_coord\":939,\"y_coord\":467,\"linked_seats\":[]},{\"place\":\"8\",\"row\":\"3\",\"x_coord\":922,\"y_coord\":457,\"linked_seats\":[]},{\"place\":\"9\",\"row\":\"3\",\"x_coord\":904,\"y_coord\":447,\"linked_seats\":[]},{\"place\":\"10\",\"row\":\"3\",\"x_coord\":887,\"y_coord\":438,\"linked_seats\":[]},{\"place\":\"11\",\"row\":\"3\",\"x_coord\":868,\"y_coord\":429,\"linked_seats\":[]},{\"place\":\"12\",\"row\":\"3\",\"x_coord\":850,\"y_coord\":421,\"linked_seats\":[]},{\"place\":\"13\",\"row\":\"3\",\"x_coord\":831,\"y_coord\":414,\"linked_seats\":[]},{\"place\":\"14\",\"row\":\"3\",\"x_coord\":775,\"y_coord\":397,\"linked_seats\":[]},{\"place\":\"15\",\"row\":\"3\",\"x_coord\":756,\"y_coord\":392,\"linked_seats\":[]},{\"place\":\"16\",\"row\":\"3\",\"x_coord\":737,\"y_coord\":388,\"linked_seats\":[]},{\"place\":\"17\",\"row\":\"3\",\"x_coord\":718,\"y_coord\":385,\"linked_seats\":[]},{\"place\":\"18\",\"row\":\"3\",\"x_coord\":699,\"y_coord\":383,\"linked_seats\":[]},{\"place\":\"19\",\"row\":\"3\",\"x_coord\":679,\"y_coord\":381,\"linked_seats\":[]},{\"place\":\"20\",\"row\":\"3\",\"x_coord\":660,\"y_coord\":379,\"linked_seats\":[]},{\"place\":\"21\",\"row\":\"3\",\"x_coord\":641,\"y_coord\":379,\"linked_seats\":[]},{\"place\":\"22\",\"row\":\"3\",\"x_coord\":621,\"y_coord\":379,\"linked_seats\":[]},{\"place\":\"23\",\"row\":\"3\",\"x_coord\":602,\"y_coord\":379,\"linked_seats\":[]},{\"place\":\"24\",\"row\":\"3\",\"x_coord\":582,\"y_coord\":381,\"linked_seats\":[]},{\"place\":\"25\",\"row\":\"3\",\"x_coord\":563,\"y_coord\":383,\"linked_seats\":[]},{\"place\":\"26\",\"row\":\"3\",\"x_coord\":544,\"y_coord\":385,\"linked_seats\":[]},{\"place\":\"27\",\"row\":\"3\",\"x_coord\":525,\"y_coord\":388,\"linked_seats\":[]},{\"place\":\"28\",\"row\":\"3\",\"x_coord\":505,\"y_coord\":392,\"linked_seats\":[]},{\"place\":\"29\",\"row\":\"3\",\"x_coord\":487,\"y_coord\":397,\"linked_seats\":[]},{\"place\":\"30\",\"row\":\"3\",\"x_coord\":431,\"y_coord\":414,\"linked_seats\":[]},{\"place\":\"31\",\"row\":\"3\",\"x_coord\":412,\"y_coord\":421,\"linked_seats\":[]},{\"place\":\"32\",\"row\":\"3\",\"x_coord\":394,\"y_coord\":429,\"linked_seats\":[]},{\"place\":\"33\",\"row\":\"3\",\"x_coord\":375,\"y_coord\":437,\"linked_seats\":[]},{\"place\":\"34\",\"row\":\"3\",\"x_coord\":358,\"y_coord\":447,\"linked_seats\":[]},{\"place\":\"35\",\"row\":\"3\",\"x_coord\":340,\"y_coord\":456,\"linked_seats\":[]},{\"place\":\"36\",\"row\":\"3\",\"x_coord\":323,\"y_coord\":467,\"linked_seats\":[]},{\"place\":\"37\",\"row\":\"3\",\"x_coord\":306,\"y_coord\":478,\"linked_seats\":[]},{\"place\":\"38\",\"row\":\"3\",\"x_coord\":289,\"y_coord\":489,\"linked_seats\":[]},{\"place\":\"39\",\"row\":\"3\",\"x_coord\":273,\"y_coord\":502,\"linked_seats\":[]},{\"place\":\"40\",\"row\":\"3\",\"x_coord\":257,\"y_coord\":514,\"linked_seats\":[]},{\"place\":\"41\",\"row\":\"3\",\"x_coord\":242,\"y_coord\":527,\"linked_seats\":[]},{\"place\":\"42\",\"row\":\"3\",\"x_coord\":227,\"y_coord\":541,\"linked_seats\":[]},{\"place\":\"1\",\"row\":\"4\",\"x_coord\":1041,\"y_coord\":518,\"linked_seats\":[]},{\"place\":\"2\",\"row\":\"4\",\"x_coord\":1027,\"y_coord\":504,\"linked_seats\":[]},{\"place\":\"3\",\"row\":\"4\",\"x_coord\":1011,\"y_coord\":492,\"linked_seats\":[]},{\"place\":\"4\",\"row\":\"4\",\"x_coord\":996,\"y_coord\":479,\"linked_seats\":[]},{\"place\":\"5\",\"row\":\"4\",\"x_coord\":980,\"y_coord\":468,\"linked_seats\":[]},{\"place\":\"6\",\"row\":\"4\",\"x_coord\":963,\"y_coord\":456,\"linked_seats\":[]},{\"place\":\"7\",\"row\":\"4\",\"x_coord\":946,\"y_coord\":446,\"linked_seats\":[]},{\"place\":\"8\",\"row\":\"4\",\"x_coord\":929,\"y_coord\":435,\"linked_seats\":[]},{\"place\":\"9\",\"row\":\"4\",\"x_coord\":912,\"y_coord\":426,\"linked_seats\":[]},{\"place\":\"10\",\"row\":\"4\",\"x_coord\":894,\"y_coord\":417,\"linked_seats\":[]},{\"place\":\"11\",\"row\":\"4\",\"x_coord\":876,\"y_coord\":408,\"linked_seats\":[]},{\"place\":\"12\",\"row\":\"4\",\"x_coord\":857,\"y_coord\":401,\"linked_seats\":[]},{\"place\":\"13\",\"row\":\"4\",\"x_coord\":839,\"y_coord\":393,\"linked_seats\":[]},{\"place\":\"14\",\"row\":\"4\",\"x_coord\":783,\"y_coord\":376,\"linked_seats\":[]},{\"place\":\"15\",\"row\":\"4\",\"x_coord\":763,\"y_coord\":371,\"linked_seats\":[]},{\"place\":\"16\",\"row\":\"4\",\"x_coord\":743,\"y_coord\":367,\"linked_seats\":[]},{\"place\":\"17\",\"row\":\"4\",\"x_coord\":723,\"y_coord\":364,\"linked_seats\":[]},{\"place\":\"18\",\"row\":\"4\",\"x_coord\":702,\"y_coord\":361,\"linked_seats\":[]},{\"place\":\"19\",\"row\":\"4\",\"x_coord\":682,\"y_coord\":359,\"linked_seats\":[]},{\"place\":\"20\",\"row\":\"4\",\"x_coord\":662,\"y_coord\":357,\"linked_seats\":[]},{\"place\":\"21\",\"row\":\"4\",\"x_coord\":641,\"y_coord\":357,\"linked_seats\":[]},{\"place\":\"22\",\"row\":\"4\",\"x_coord\":621,\"y_coord\":357,\"linked_seats\":[]},{\"place\":\"23\",\"row\":\"4\",\"x_coord\":600,\"y_coord\":357,\"linked_seats\":[]},{\"place\":\"24\",\"row\":\"4\",\"x_coord\":580,\"y_coord\":359,\"linked_seats\":[]},{\"place\":\"25\",\"row\":\"4\",\"x_coord\":559,\"y_coord\":361,\"linked_seats\":[]},{\"place\":\"26\",\"row\":\"4\",\"x_coord\":539,\"y_coord\":364,\"linked_seats\":[]},{\"place\":\"27\",\"row\":\"4\",\"x_coord\":519,\"y_coord\":367,\"linked_seats\":[]},{\"place\":\"28\",\"row\":\"4\",\"x_coord\":499,\"y_coord\":371,\"linked_seats\":[]},{\"place\":\"29\",\"row\":\"4\",\"x_coord\":479,\"y_coord\":376,\"linked_seats\":[]},{\"place\":\"30\",\"row\":\"4\",\"x_coord\":423,\"y_coord\":393,\"linked_seats\":[]},{\"place\":\"31\",\"row\":\"4\",\"x_coord\":404,\"y_coord\":401,\"linked_seats\":[]},{\"place\":\"32\",\"row\":\"4\",\"x_coord\":386,\"y_coord\":408,\"linked_seats\":[]},{\"place\":\"33\",\"row\":\"4\",\"x_coord\":368,\"y_coord\":417,\"linked_seats\":[]},{\"place\":\"34\",\"row\":\"4\",\"x_coord\":350,\"y_coord\":426,\"linked_seats\":[]},{\"place\":\"35\",\"row\":\"4\",\"x_coord\":332,\"y_coord\":435,\"linked_seats\":[]},{\"place\":\"36\",\"row\":\"4\",\"x_coord\":315,\"y_coord\":446,\"linked_seats\":[]},{\"place\":\"37\",\"row\":\"4\",\"x_coord\":298,\"y_coord\":456,\"linked_seats\":[]},{\"place\":\"38\",\"row\":\"4\",\"x_coord\":282,\"y_coord\":468,\"linked_seats\":[]},{\"place\":\"39\",\"row\":\"4\",\"x_coord\":266,\"y_coord\":479,\"linked_seats\":[]},{\"place\":\"40\",\"row\":\"4\",\"x_coord\":250,\"y_coord\":492,\"linked_seats\":[]},{\"place\":\"41\",\"row\":\"4\",\"x_coord\":235,\"y_coord\":505,\"linked_seats\":[]},{\"place\":\"42\",\"row\":\"4\",\"x_coord\":220,\"y_coord\":518,\"linked_seats\":[]},{\"place\":\"1\",\"row\":\"5\",\"x_coord\":1050,\"y_coord\":496,\"linked_seats\":[]},{\"place\":\"2\",\"row\":\"5\",\"x_coord\":1035,\"y_coord\":483,\"linked_seats\":[]},{\"place\":\"3\",\"row\":\"5\",\"x_coord\":1019,\"y_coord\":470,\"linked_seats\":[]},{\"place\":\"4\",\"row\":\"5\",\"x_coord\":1004,\"y_coord\":458,\"linked_seats\":[]},{\"place\":\"5\",\"row\":\"5\",\"x_coord\":987,\"y_coord\":446,\"linked_seats\":[]},{\"place\":\"6\",\"row\":\"5\",\"x_coord\":971,\"y_coord\":435,\"linked_seats\":[]},{\"place\":\"7\",\"row\":\"5\",\"x_coord\":954,\"y_coord\":424,\"linked_seats\":[]},{\"place\":\"8\",\"row\":\"5\",\"x_coord\":937,\"y_coord\":414,\"linked_seats\":[]},{\"place\":\"9\",\"row\":\"5\",\"x_coord\":919,\"y_coord\":405,\"linked_seats\":[]},{\"place\":\"10\",\"row\":\"5\",\"x_coord\":901,\"y_coord\":396,\"linked_seats\":[]},{\"place\":\"11\",\"row\":\"5\",\"x_coord\":883,\"y_coord\":388,\"linked_seats\":[]},{\"place\":\"12\",\"row\":\"5\",\"x_coord\":865,\"y_coord\":380,\"linked_seats\":[]},{\"place\":\"13\",\"row\":\"5\",\"x_coord\":846,\"y_coord\":373,\"linked_seats\":[]},{\"place\":\"14\",\"row\":\"5\",\"x_coord\":790,\"y_coord\":355,\"linked_seats\":[]},{\"place\":\"15\",\"row\":\"5\",\"x_coord\":771,\"y_coord\":350,\"linked_seats\":[]},{\"place\":\"16\",\"row\":\"5\",\"x_coord\":751,\"y_coord\":346,\"linked_seats\":[]},{\"place\":\"17\",\"row\":\"5\",\"x_coord\":731,\"y_coord\":343,\"linked_seats\":[]},{\"place\":\"18\",\"row\":\"5\",\"x_coord\":711,\"y_coord\":340,\"linked_seats\":[]},{\"place\":\"19\",\"row\":\"5\",\"x_coord\":691,\"y_coord\":338,\"linked_seats\":[]},{\"place\":\"20\",\"row\":\"5\",\"x_coord\":671,\"y_coord\":336,\"linked_seats\":[]},{\"place\":\"21\",\"row\":\"5\",\"x_coord\":651,\"y_coord\":335,\"linked_seats\":[]},{\"place\":\"22\",\"row\":\"5\",\"x_coord\":630,\"y_coord\":335,\"linked_seats\":[]},{\"place\":\"23\",\"row\":\"5\",\"x_coord\":610,\"y_coord\":335,\"linked_seats\":[]},{\"place\":\"24\",\"row\":\"5\",\"x_coord\":590,\"y_coord\":336,\"linked_seats\":[]},{\"place\":\"25\",\"row\":\"5\",\"x_coord\":570,\"y_coord\":338,\"linked_seats\":[]},{\"place\":\"26\",\"row\":\"5\",\"x_coord\":550,\"y_coord\":340,\"linked_seats\":[]},{\"place\":\"27\",\"row\":\"5\",\"x_coord\":530,\"y_coord\":343,\"linked_seats\":[]},{\"place\":\"28\",\"row\":\"5\",\"x_coord\":510,\"y_coord\":346,\"linked_seats\":[]},{\"place\":\"29\",\"row\":\"5\",\"x_coord\":490,\"y_coord\":350,\"linked_seats\":[]},{\"place\":\"30\",\"row\":\"5\",\"x_coord\":471,\"y_coord\":355,\"linked_seats\":[]},{\"place\":\"31\",\"row\":\"5\",\"x_coord\":416,\"y_coord\":373,\"linked_seats\":[]},{\"place\":\"32\",\"row\":\"5\",\"x_coord\":397,\"y_coord\":380,\"linked_seats\":[]},{\"place\":\"33\",\"row\":\"5\",\"x_coord\":379,\"y_coord\":387,\"linked_seats\":[]},{\"place\":\"34\",\"row\":\"5\",\"x_coord\":360,\"y_coord\":396,\"linked_seats\":[]},{\"place\":\"35\",\"row\":\"5\",\"x_coord\":343,\"y_coord\":405,\"linked_seats\":[]},{\"place\":\"36\",\"row\":\"5\",\"x_coord\":325,\"y_coord\":414,\"linked_seats\":[]},{\"place\":\"37\",\"row\":\"5\",\"x_coord\":308,\"y_coord\":424,\"linked_seats\":[]},{\"place\":\"38\",\"row\":\"5\",\"x_coord\":291,\"y_coord\":435,\"linked_seats\":[]},{\"place\":\"39\",\"row\":\"5\",\"x_coord\":274,\"y_coord\":446,\"linked_seats\":[]},{\"place\":\"40\",\"row\":\"5\",\"x_coord\":258,\"y_coord\":458,\"linked_seats\":[]},{\"place\":\"41\",\"row\":\"5\",\"x_coord\":242,\"y_coord\":470,\"linked_seats\":[]},{\"place\":\"42\",\"row\":\"5\",\"x_coord\":226,\"y_coord\":483,\"linked_seats\":[]},{\"place\":\"43\",\"row\":\"5\",\"x_coord\":211,\"y_coord\":496,\"linked_seats\":[]},{\"place\":\"1\",\"row\":\"6\",\"x_coord\":1058,\"y_coord\":473,\"linked_seats\":[]},{\"place\":\"2\",\"row\":\"6\",\"x_coord\":1043,\"y_coord\":460,\"linked_seats\":[]},{\"place\":\"3\",\"row\":\"6\",\"x_coord\":1027,\"y_coord\":448,\"linked_seats\":[]},{\"place\":\"4\",\"row\":\"6\",\"x_coord\":1011,\"y_coord\":436,\"linked_seats\":[]},{\"place\":\"5\",\"row\":\"6\",\"x_coord\":995,\"y_coord\":425,\"linked_seats\":[]},{\"place\":\"6\",\"row\":\"6\",\"x_coord\":978,\"y_coord\":414,\"linked_seats\":[]},{\"place\":\"7\",\"row\":\"6\",\"x_coord\":961,\"y_coord\":403,\"linked_seats\":[]},{\"place\":\"8\",\"row\":\"6\",\"x_coord\":944,\"y_coord\":393,\"linked_seats\":[]},{\"place\":\"9\",\"row\":\"6\",\"x_coord\":927,\"y_coord\":384,\"linked_seats\":[]},{\"place\":\"10\",\"row\":\"6\",\"x_coord\":909,\"y_coord\":375,\"linked_seats\":[]},{\"place\":\"11\",\"row\":\"6\",\"x_coord\":891,\"y_coord\":367,\"linked_seats\":[]},{\"place\":\"12\",\"row\":\"6\",\"x_coord\":872,\"y_coord\":359,\"linked_seats\":[]},{\"place\":\"13\",\"row\":\"6\",\"x_coord\":854,\"y_coord\":352,\"linked_seats\":[]},{\"place\":\"14\",\"row\":\"6\",\"x_coord\":798,\"y_coord\":334,\"linked_seats\":[]},{\"place\":\"15\",\"row\":\"6\",\"x_coord\":779,\"y_coord\":330,\"linked_seats\":[]},{\"place\":\"16\",\"row\":\"6\",\"x_coord\":759,\"y_coord\":325,\"linked_seats\":[]},{\"place\":\"17\",\"row\":\"6\",\"x_coord\":740,\"y_coord\":322,\"linked_seats\":[]},{\"place\":\"18\",\"row\":\"6\",\"x_coord\":720,\"y_coord\":319,\"linked_seats\":[]},{\"place\":\"19\",\"row\":\"6\",\"x_coord\":700,\"y_coord\":316,\"linked_seats\":[]},{\"place\":\"20\",\"row\":\"6\",\"x_coord\":681,\"y_coord\":315,\"linked_seats\":[]},{\"place\":\"21\",\"row\":\"6\",\"x_coord\":661,\"y_coord\":313,\"linked_seats\":[]},{\"place\":\"22\",\"row\":\"6\",\"x_coord\":641,\"y_coord\":313,\"linked_seats\":[]},{\"place\":\"23\",\"row\":\"6\",\"x_coord\":621,\"y_coord\":313,\"linked_seats\":[]},{\"place\":\"24\",\"row\":\"6\",\"x_coord\":601,\"y_coord\":313,\"linked_seats\":[]},{\"place\":\"25\",\"row\":\"6\",\"x_coord\":581,\"y_coord\":315,\"linked_seats\":[]},{\"place\":\"26\",\"row\":\"6\",\"x_coord\":562,\"y_coord\":316,\"linked_seats\":[]},{\"place\":\"27\",\"row\":\"6\",\"x_coord\":542,\"y_coord\":319,\"linked_seats\":[]},{\"place\":\"28\",\"row\":\"6\",\"x_coord\":522,\"y_coord\":322,\"linked_seats\":[]},{\"place\":\"29\",\"row\":\"6\",\"x_coord\":503,\"y_coord\":325,\"linked_seats\":[]},{\"place\":\"30\",\"row\":\"6\",\"x_coord\":483,\"y_coord\":330,\"linked_seats\":[]},{\"place\":\"31\",\"row\":\"6\",\"x_coord\":464,\"y_coord\":334,\"linked_seats\":[]},{\"place\":\"32\",\"row\":\"6\",\"x_coord\":408,\"y_coord\":352,\"linked_seats\":[]},{\"place\":\"33\",\"row\":\"6\",\"x_coord\":390,\"y_coord\":359,\"linked_seats\":[]},{\"place\":\"34\",\"row\":\"6\",\"x_coord\":371,\"y_coord\":367,\"linked_seats\":[]},{\"place\":\"35\",\"row\":\"6\",\"x_coord\":353,\"y_coord\":375,\"linked_seats\":[]},{\"place\":\"36\",\"row\":\"6\",\"x_coord\":335,\"y_coord\":384,\"linked_seats\":[]},{\"place\":\"37\",\"row\":\"6\",\"x_coord\":318,\"y_coord\":393,\"linked_seats\":[]},{\"place\":\"38\",\"row\":\"6\",\"x_coord\":300,\"y_coord\":403,\"linked_seats\":[]},{\"place\":\"39\",\"row\":\"6\",\"x_coord\":283,\"y_coord\":414,\"linked_seats\":[]},{\"place\":\"40\",\"row\":\"6\",\"x_coord\":267,\"y_coord\":425,\"linked_seats\":[]},{\"place\":\"41\",\"row\":\"6\",\"x_coord\":250,\"y_coord\":436,\"linked_seats\":[]},{\"place\":\"42\",\"row\":\"6\",\"x_coord\":234,\"y_coord\":448,\"linked_seats\":[]},{\"place\":\"43\",\"row\":\"6\",\"x_coord\":219,\"y_coord\":461,\"linked_seats\":[]},{\"place\":\"44\",\"row\":\"6\",\"x_coord\":204,\"y_coord\":473,\"linked_seats\":[]},{\"place\":\"1\",\"row\":\"7\",\"x_coord\":1066,\"y_coord\":451,\"linked_seats\":[]},{\"place\":\"2\",\"row\":\"7\",\"x_coord\":1051,\"y_coord\":438,\"linked_seats\":[]},{\"place\":\"3\",\"row\":\"7\",\"x_coord\":1035,\"y_coord\":426,\"linked_seats\":[]},{\"place\":\"4\",\"row\":\"7\",\"x_coord\":1019,\"y_coord\":414,\"linked_seats\":[]},{\"place\":\"5\",\"row\":\"7\",\"x_coord\":1002,\"y_coord\":403,\"linked_seats\":[]},{\"place\":\"6\",\"row\":\"7\",\"x_coord\":986,\"y_coord\":392,\"linked_seats\":[]},{\"place\":\"7\",\"row\":\"7\",\"x_coord\":969,\"y_coord\":382,\"linked_seats\":[]},{\"place\":\"8\",\"row\":\"7\",\"x_coord\":951,\"y_coord\":372,\"linked_seats\":[]},{\"place\":\"9\",\"row\":\"7\",\"x_coord\":934,\"y_coord\":363,\"linked_seats\":[]},{\"place\":\"10\",\"row\":\"7\",\"x_coord\":916,\"y_coord\":354,\"linked_seats\":[]},{\"place\":\"11\",\"row\":\"7\",\"x_coord\":898,\"y_coord\":346,\"linked_seats\":[]},{\"place\":\"12\",\"row\":\"7\",\"x_coord\":879,\"y_coord\":338,\"linked_seats\":[]},{\"place\":\"13\",\"row\":\"7\",\"x_coord\":861,\"y_coord\":331,\"linked_seats\":[]},{\"place\":\"14\",\"row\":\"7\",\"x_coord\":805,\"y_coord\":314,\"linked_seats\":[]},{\"place\":\"15\",\"row\":\"7\",\"x_coord\":785,\"y_coord\":308,\"linked_seats\":[]},{\"place\":\"16\",\"row\":\"7\",\"x_coord\":765,\"y_coord\":304,\"linked_seats\":[]},{\"place\":\"17\",\"row\":\"7\",\"x_coord\":744,\"y_coord\":300,\"linked_seats\":[]},{\"place\":\"18\",\"row\":\"7\",\"x_coord\":724,\"y_coord\":297,\"linked_seats\":[]},{\"place\":\"19\",\"row\":\"7\",\"x_coord\":703,\"y_coord\":295,\"linked_seats\":[]},{\"place\":\"20\",\"row\":\"7\",\"x_coord\":683,\"y_coord\":293,\"linked_seats\":[]},{\"place\":\"21\",\"row\":\"7\",\"x_coord\":662,\"y_coord\":291,\"linked_seats\":[]},{\"place\":\"22\",\"row\":\"7\",\"x_coord\":641,\"y_coord\":291,\"linked_seats\":[]},{\"place\":\"23\",\"row\":\"7\",\"x_coord\":621,\"y_coord\":291,\"linked_seats\":[]},{\"place\":\"24\",\"row\":\"7\",\"x_coord\":600,\"y_coord\":291,\"linked_seats\":[]},{\"place\":\"25\",\"row\":\"7\",\"x_coord\":579,\"y_coord\":293,\"linked_seats\":[]},{\"place\":\"26\",\"row\":\"7\",\"x_coord\":559,\"y_coord\":295,\"linked_seats\":[]},{\"place\":\"27\",\"row\":\"7\",\"x_coord\":538,\"y_coord\":297,\"linked_seats\":[]},{\"place\":\"28\",\"row\":\"7\",\"x_coord\":518,\"y_coord\":300,\"linked_seats\":[]},{\"place\":\"29\",\"row\":\"7\",\"x_coord\":497,\"y_coord\":304,\"linked_seats\":[]},{\"place\":\"30\",\"row\":\"7\",\"x_coord\":477,\"y_coord\":308,\"linked_seats\":[]},{\"place\":\"31\",\"row\":\"7\",\"x_coord\":457,\"y_coord\":313,\"linked_seats\":[]},{\"place\":\"32\",\"row\":\"7\",\"x_coord\":400,\"y_coord\":331,\"linked_seats\":[]},{\"place\":\"33\",\"row\":\"7\",\"x_coord\":382,\"y_coord\":338,\"linked_seats\":[]},{\"place\":\"34\",\"row\":\"7\",\"x_coord\":364,\"y_coord\":346,\"linked_seats\":[]},{\"place\":\"35\",\"row\":\"7\",\"x_coord\":345,\"y_coord\":354,\"linked_seats\":[]},{\"place\":\"36\",\"row\":\"7\",\"x_coord\":328,\"y_coord\":363,\"linked_seats\":[]},{\"place\":\"37\",\"row\":\"7\",\"x_coord\":310,\"y_coord\":372,\"linked_seats\":[]},{\"place\":\"38\",\"row\":\"7\",\"x_coord\":293,\"y_coord\":382,\"linked_seats\":[]},{\"place\":\"39\",\"row\":\"7\",\"x_coord\":276,\"y_coord\":392,\"linked_seats\":[]},{\"place\":\"40\",\"row\":\"7\",\"x_coord\":259,\"y_coord\":403,\"linked_seats\":[]},{\"place\":\"41\",\"row\":\"7\",\"x_coord\":243,\"y_coord\":414,\"linked_seats\":[]},{\"place\":\"42\",\"row\":\"7\",\"x_coord\":227,\"y_coord\":426,\"linked_seats\":[]},{\"place\":\"43\",\"row\":\"7\",\"x_coord\":211,\"y_coord\":438,\"linked_seats\":[]},{\"place\":\"44\",\"row\":\"7\",\"x_coord\":196,\"y_coord\":451,\"linked_seats\":[]},{\"place\":\"1\",\"row\":\"8\",\"x_coord\":1074,\"y_coord\":429,\"linked_seats\":[]},{\"place\":\"2\",\"row\":\"8\",\"x_coord\":1058,\"y_coord\":416,\"linked_seats\":[]},{\"place\":\"3\",\"row\":\"8\",\"x_coord\":1042,\"y_coord\":404,\"linked_seats\":[]},{\"place\":\"4\",\"row\":\"8\",\"x_coord\":1026,\"y_coord\":393,\"linked_seats\":[]},{\"place\":\"5\",\"row\":\"8\",\"x_coord\":1010,\"y_coord\":382,\"linked_seats\":[]},{\"place\":\"6\",\"row\":\"8\",\"x_coord\":993,\"y_coord\":371,\"linked_seats\":[]},{\"place\":\"7\",\"row\":\"8\",\"x_coord\":976,\"y_coord\":361,\"linked_seats\":[]},{\"place\":\"8\",\"row\":\"8\",\"x_coord\":959,\"y_coord\":351,\"linked_seats\":[]},{\"place\":\"9\",\"row\":\"8\",\"x_coord\":941,\"y_coord\":342,\"linked_seats\":[]},{\"place\":\"10\",\"row\":\"8\",\"x_coord\":923,\"y_coord\":333,\"linked_seats\":[]},{\"place\":\"11\",\"row\":\"8\",\"x_coord\":905,\"y_coord\":325,\"linked_seats\":[]},{\"place\":\"12\",\"row\":\"8\",\"x_coord\":887,\"y_coord\":318,\"linked_seats\":[]},{\"place\":\"13\",\"row\":\"8\",\"x_coord\":868,\"y_coord\":310,\"linked_seats\":[]},{\"place\":\"14\",\"row\":\"8\",\"x_coord\":812,\"y_coord\":293,\"linked_seats\":[]},{\"place\":\"15\",\"row\":\"8\",\"x_coord\":793,\"y_coord\":288,\"linked_seats\":[]},{\"place\":\"16\",\"row\":\"8\",\"x_coord\":773,\"y_coord\":283,\"linked_seats\":[]},{\"place\":\"17\",\"row\":\"8\",\"x_coord\":753,\"y_coord\":279,\"linked_seats\":[]},{\"place\":\"18\",\"row\":\"8\",\"x_coord\":733,\"y_coord\":276,\"linked_seats\":[]},{\"place\":\"19\",\"row\":\"8\",\"x_coord\":712,\"y_coord\":273,\"linked_seats\":[]},{\"place\":\"20\",\"row\":\"8\",\"x_coord\":692,\"y_coord\":271,\"linked_seats\":[]},{\"place\":\"21\",\"row\":\"8\",\"x_coord\":672,\"y_coord\":270,\"linked_seats\":[]},{\"place\":\"22\",\"row\":\"8\",\"x_coord\":651,\"y_coord\":269,\"linked_seats\":[]},{\"place\":\"23\",\"row\":\"8\",\"x_coord\":631,\"y_coord\":269,\"linked_seats\":[]},{\"place\":\"24\",\"row\":\"8\",\"x_coord\":610,\"y_coord\":269,\"linked_seats\":[]},{\"place\":\"25\",\"row\":\"8\",\"x_coord\":590,\"y_coord\":270,\"linked_seats\":[]},{\"place\":\"26\",\"row\":\"8\",\"x_coord\":570,\"y_coord\":271,\"linked_seats\":[]},{\"place\":\"27\",\"row\":\"8\",\"x_coord\":549,\"y_coord\":273,\"linked_seats\":[]},{\"place\":\"28\",\"row\":\"8\",\"x_coord\":529,\"y_coord\":276,\"linked_seats\":[]},{\"place\":\"29\",\"row\":\"8\",\"x_coord\":509,\"y_coord\":279,\"linked_seats\":[]},{\"place\":\"30\",\"row\":\"8\",\"x_coord\":489,\"y_coord\":283,\"linked_seats\":[]},{\"place\":\"31\",\"row\":\"8\",\"x_coord\":469,\"y_coord\":288,\"linked_seats\":[]},{\"place\":\"32\",\"row\":\"8\",\"x_coord\":449,\"y_coord\":293,\"linked_seats\":[]},{\"place\":\"33\",\"row\":\"8\",\"x_coord\":394,\"y_coord\":310,\"linked_seats\":[]},{\"place\":\"34\",\"row\":\"8\",\"x_coord\":375,\"y_coord\":317,\"linked_seats\":[]},{\"place\":\"35\",\"row\":\"8\",\"x_coord\":357,\"y_coord\":325,\"linked_seats\":[]},{\"place\":\"36\",\"row\":\"8\",\"x_coord\":339,\"y_coord\":333,\"linked_seats\":[]},{\"place\":\"37\",\"row\":\"8\",\"x_coord\":321,\"y_coord\":342,\"linked_seats\":[]},{\"place\":\"38\",\"row\":\"8\",\"x_coord\":303,\"y_coord\":351,\"linked_seats\":[]},{\"place\":\"39\",\"row\":\"8\",\"x_coord\":285,\"y_coord\":361,\"linked_seats\":[]},{\"place\":\"40\",\"row\":\"8\",\"x_coord\":268,\"y_coord\":371,\"linked_seats\":[]},{\"place\":\"41\",\"row\":\"8\",\"x_coord\":251,\"y_coord\":382,\"linked_seats\":[]},{\"place\":\"42\",\"row\":\"8\",\"x_coord\":235,\"y_coord\":393,\"linked_seats\":[]},{\"place\":\"43\",\"row\":\"8\",\"x_coord\":219,\"y_coord\":405,\"linked_seats\":[]},{\"place\":\"44\",\"row\":\"8\",\"x_coord\":203,\"y_coord\":417,\"linked_seats\":[]},{\"place\":\"45\",\"row\":\"8\",\"x_coord\":187,\"y_coord\":429,\"linked_seats\":[]},{\"place\":\"1\",\"row\":\"9\",\"x_coord\":1082,\"y_coord\":408,\"linked_seats\":[]},{\"place\":\"2\",\"row\":\"9\",\"x_coord\":1067,\"y_coord\":395,\"linked_seats\":[]},{\"place\":\"3\",\"row\":\"9\",\"x_coord\":1051,\"y_coord\":383,\"linked_seats\":[]},{\"place\":\"4\",\"row\":\"9\",\"x_coord\":1034,\"y_coord\":372,\"linked_seats\":[]},{\"place\":\"5\",\"row\":\"9\",\"x_coord\":1018,\"y_coord\":361,\"linked_seats\":[]},{\"place\":\"6\",\"row\":\"9\",\"x_coord\":1001,\"y_coord\":350,\"linked_seats\":[]},{\"place\":\"7\",\"row\":\"9\",\"x_coord\":984,\"y_coord\":340,\"linked_seats\":[]},{\"place\":\"8\",\"row\":\"9\",\"x_coord\":966,\"y_coord\":330,\"linked_seats\":[]},{\"place\":\"9\",\"row\":\"9\",\"x_coord\":949,\"y_coord\":321,\"linked_seats\":[]},{\"place\":\"10\",\"row\":\"9\",\"x_coord\":931,\"y_coord\":313,\"linked_seats\":[]},{\"place\":\"11\",\"row\":\"9\",\"x_coord\":913,\"y_coord\":304,\"linked_seats\":[]},{\"place\":\"12\",\"row\":\"9\",\"x_coord\":894,\"y_coord\":297,\"linked_seats\":[]},{\"place\":\"13\",\"row\":\"9\",\"x_coord\":875,\"y_coord\":290,\"linked_seats\":[]},{\"place\":\"14\",\"row\":\"9\",\"x_coord\":820,\"y_coord\":272,\"linked_seats\":[]},{\"place\":\"15\",\"row\":\"9\",\"x_coord\":800,\"y_coord\":267,\"linked_seats\":[]},{\"place\":\"16\",\"row\":\"9\",\"x_coord\":781,\"y_coord\":262,\"linked_seats\":[]},{\"place\":\"17\",\"row\":\"9\",\"x_coord\":761,\"y_coord\":259,\"linked_seats\":[]},{\"place\":\"18\",\"row\":\"9\",\"x_coord\":741,\"y_coord\":255,\"linked_seats\":[]},{\"place\":\"19\",\"row\":\"9\",\"x_coord\":721,\"y_coord\":252,\"linked_seats\":[]},{\"place\":\"20\",\"row\":\"9\",\"x_coord\":701,\"y_coord\":250,\"linked_seats\":[]},{\"place\":\"21\",\"row\":\"9\",\"x_coord\":681,\"y_coord\":248,\"linked_seats\":[]},{\"place\":\"22\",\"row\":\"9\",\"x_coord\":661,\"y_coord\":247,\"linked_seats\":[]},{\"place\":\"23\",\"row\":\"9\",\"x_coord\":641,\"y_coord\":247,\"linked_seats\":[]},{\"place\":\"24\",\"row\":\"9\",\"x_coord\":621,\"y_coord\":247,\"linked_seats\":[]},{\"place\":\"25\",\"row\":\"9\",\"x_coord\":601,\"y_coord\":247,\"linked_seats\":[]},{\"place\":\"26\",\"row\":\"9\",\"x_coord\":581,\"y_coord\":248,\"linked_seats\":[]},{\"place\":\"27\",\"row\":\"9\",\"x_coord\":561,\"y_coord\":250,\"linked_seats\":[]},{\"place\":\"28\",\"row\":\"9\",\"x_coord\":541,\"y_coord\":252,\"linked_seats\":[]},{\"place\":\"29\",\"row\":\"9\",\"x_coord\":521,\"y_coord\":255,\"linked_seats\":[]},{\"place\":\"30\",\"row\":\"9\",\"x_coord\":501,\"y_coord\":258,\"linked_seats\":[]},{\"place\":\"31\",\"row\":\"9\",\"x_coord\":482,\"y_coord\":262,\"linked_seats\":[]},{\"place\":\"32\",\"row\":\"9\",\"x_coord\":462,\"y_coord\":267,\"linked_seats\":[]},{\"place\":\"33\",\"row\":\"9\",\"x_coord\":442,\"y_coord\":272,\"linked_seats\":[]},{\"place\":\"34\",\"row\":\"9\",\"x_coord\":387,\"y_coord\":290,\"linked_seats\":[]},{\"place\":\"35\",\"row\":\"9\",\"x_coord\":368,\"y_coord\":297,\"linked_seats\":[]},{\"place\":\"36\",\"row\":\"9\",\"x_coord\":350,\"y_coord\":304,\"linked_seats\":[]},{\"place\":\"37\",\"row\":\"9\",\"x_coord\":331,\"y_coord\":312,\"linked_seats\":[]},{\"place\":\"38\",\"row\":\"9\",\"x_coord\":313,\"y_coord\":321,\"linked_seats\":[]},{\"place\":\"39\",\"row\":\"9\",\"x_coord\":296,\"y_coord\":330,\"linked_seats\":[]},{\"place\":\"40\",\"row\":\"9\",\"x_coord\":278,\"y_coord\":340,\"linked_seats\":[]},{\"place\":\"41\",\"row\":\"9\",\"x_coord\":261,\"y_coord\":350,\"linked_seats\":[]},{\"place\":\"42\",\"row\":\"9\",\"x_coord\":244,\"y_coord\":360,\"linked_seats\":[]},{\"place\":\"43\",\"row\":\"9\",\"x_coord\":228,\"y_coord\":371,\"linked_seats\":[]},{\"place\":\"44\",\"row\":\"9\",\"x_coord\":211,\"y_coord\":383,\"linked_seats\":[]},{\"place\":\"45\",\"row\":\"9\",\"x_coord\":195,\"y_coord\":395,\"linked_seats\":[]},{\"place\":\"46\",\"row\":\"9\",\"x_coord\":180,\"y_coord\":407,\"linked_seats\":[]},{\"place\":\"1\",\"row\":\"10\",\"x_coord\":1090,\"y_coord\":385,\"linked_seats\":[]},{\"place\":\"2\",\"row\":\"10\",\"x_coord\":1074,\"y_coord\":373,\"linked_seats\":[]},{\"place\":\"3\",\"row\":\"10\",\"x_coord\":1058,\"y_coord\":361,\"linked_seats\":[]},{\"place\":\"4\",\"row\":\"10\",\"x_coord\":1042,\"y_coord\":350,\"linked_seats\":[]},{\"place\":\"5\",\"row\":\"10\",\"x_coord\":1025,\"y_coord\":339,\"linked_seats\":[]},{\"place\":\"6\",\"row\":\"10\",\"x_coord\":1008,\"y_coord\":329,\"linked_seats\":[]},{\"place\":\"7\",\"row\":\"10\",\"x_coord\":991,\"y_coord\":319,\"linked_seats\":[]},{\"place\":\"8\",\"row\":\"10\",\"x_coord\":974,\"y_coord\":309,\"linked_seats\":[]},{\"place\":\"9\",\"row\":\"10\",\"x_coord\":956,\"y_coord\":300,\"linked_seats\":[]},{\"place\":\"10\",\"row\":\"10\",\"x_coord\":938,\"y_coord\":292,\"linked_seats\":[]},{\"place\":\"11\",\"row\":\"10\",\"x_coord\":920,\"y_coord\":284,\"linked_seats\":[]},{\"place\":\"12\",\"row\":\"10\",\"x_coord\":902,\"y_coord\":276,\"linked_seats\":[]},{\"place\":\"13\",\"row\":\"10\",\"x_coord\":883,\"y_coord\":269,\"linked_seats\":[]},{\"place\":\"14\",\"row\":\"10\",\"x_coord\":827,\"y_coord\":251,\"linked_seats\":[]},{\"place\":\"15\",\"row\":\"10\",\"x_coord\":807,\"y_coord\":246,\"linked_seats\":[]},{\"place\":\"16\",\"row\":\"10\",\"x_coord\":787,\"y_coord\":241,\"linked_seats\":[]},{\"place\":\"17\",\"row\":\"10\",\"x_coord\":766,\"y_coord\":237,\"linked_seats\":[]},{\"place\":\"18\",\"row\":\"10\",\"x_coord\":746,\"y_coord\":234,\"linked_seats\":[]},{\"place\":\"19\",\"row\":\"10\",\"x_coord\":725,\"y_coord\":231,\"linked_seats\":[]},{\"place\":\"20\",\"row\":\"10\",\"x_coord\":704,\"y_coord\":228,\"linked_seats\":[]},{\"place\":\"21\",\"row\":\"10\",\"x_coord\":683,\"y_coord\":227,\"linked_seats\":[]},{\"place\":\"22\",\"row\":\"10\",\"x_coord\":663,\"y_coord\":225,\"linked_seats\":[]},{\"place\":\"23\",\"row\":\"10\",\"x_coord\":642,\"y_coord\":225,\"linked_seats\":[]},{\"place\":\"24\",\"row\":\"10\",\"x_coord\":621,\"y_coord\":225,\"linked_seats\":[]},{\"place\":\"25\",\"row\":\"10\",\"x_coord\":600,\"y_coord\":225,\"linked_seats\":[]},{\"place\":\"26\",\"row\":\"10\",\"x_coord\":579,\"y_coord\":226,\"linked_seats\":[]},{\"place\":\"27\",\"row\":\"10\",\"x_coord\":558,\"y_coord\":228,\"linked_seats\":[]},{\"place\":\"28\",\"row\":\"10\",\"x_coord\":538,\"y_coord\":231,\"linked_seats\":[]},{\"place\":\"29\",\"row\":\"10\",\"x_coord\":517,\"y_coord\":233,\"linked_seats\":[]},{\"place\":\"30\",\"row\":\"10\",\"x_coord\":496,\"y_coord\":237,\"linked_seats\":[]},{\"place\":\"31\",\"row\":\"10\",\"x_coord\":476,\"y_coord\":241,\"linked_seats\":[]},{\"place\":\"32\",\"row\":\"10\",\"x_coord\":455,\"y_coord\":246,\"linked_seats\":[]},{\"place\":\"33\",\"row\":\"10\",\"x_coord\":435,\"y_coord\":251,\"linked_seats\":[]},{\"place\":\"34\",\"row\":\"10\",\"x_coord\":379,\"y_coord\":269,\"linked_seats\":[]},{\"place\":\"35\",\"row\":\"10\",\"x_coord\":360,\"y_coord\":276,\"linked_seats\":[]},{\"place\":\"36\",\"row\":\"10\",\"x_coord\":342,\"y_coord\":284,\"linked_seats\":[]},{\"place\":\"37\",\"row\":\"10\",\"x_coord\":324,\"y_coord\":292,\"linked_seats\":[]},{\"place\":\"38\",\"row\":\"10\",\"x_coord\":306,\"y_coord\":300,\"linked_seats\":[]},{\"place\":\"39\",\"row\":\"10\",\"x_coord\":288,\"y_coord\":309,\"linked_seats\":[]},{\"place\":\"40\",\"row\":\"10\",\"x_coord\":271,\"y_coord\":319,\"linked_seats\":[]},{\"place\":\"41\",\"row\":\"10\",\"x_coord\":254,\"y_coord\":329,\"linked_seats\":[]},{\"place\":\"42\",\"row\":\"10\",\"x_coord\":237,\"y_coord\":339,\"linked_seats\":[]},{\"place\":\"43\",\"row\":\"10\",\"x_coord\":220,\"y_coord\":350,\"linked_seats\":[]},{\"place\":\"44\",\"row\":\"10\",\"x_coord\":204,\"y_coord\":361,\"linked_seats\":[]},{\"place\":\"45\",\"row\":\"10\",\"x_coord\":188,\"y_coord\":373,\"linked_seats\":[]},{\"place\":\"46\",\"row\":\"10\",\"x_coord\":172,\"y_coord\":385,\"linked_seats\":[]},{\"place\":\"1\",\"row\":\"11\",\"x_coord\":1098,\"y_coord\":363,\"linked_seats\":[]},{\"place\":\"2\",\"row\":\"11\",\"x_coord\":1082,\"y_coord\":351,\"linked_seats\":[]},{\"place\":\"3\",\"row\":\"11\",\"x_coord\":1066,\"y_coord\":340,\"linked_seats\":[]},{\"place\":\"4\",\"row\":\"11\",\"x_coord\":1049,\"y_coord\":329,\"linked_seats\":[]},{\"place\":\"5\",\"row\":\"11\",\"x_coord\":1033,\"y_coord\":318,\"linked_seats\":[]},{\"place\":\"6\",\"row\":\"11\",\"x_coord\":1016,\"y_coord\":308,\"linked_seats\":[]},{\"place\":\"7\",\"row\":\"11\",\"x_coord\":999,\"y_coord\":298,\"linked_seats\":[]},{\"place\":\"8\",\"row\":\"11\",\"x_coord\":981,\"y_coord\":288,\"linked_seats\":[]},{\"place\":\"9\",\"row\":\"11\",\"x_coord\":963,\"y_coord\":279,\"linked_seats\":[]},{\"place\":\"10\",\"row\":\"11\",\"x_coord\":946,\"y_coord\":271,\"linked_seats\":[]},{\"place\":\"11\",\"row\":\"11\",\"x_coord\":927,\"y_coord\":263,\"linked_seats\":[]},{\"place\":\"12\",\"row\":\"11\",\"x_coord\":909,\"y_coord\":255,\"linked_seats\":[]},{\"place\":\"13\",\"row\":\"11\",\"x_coord\":891,\"y_coord\":248,\"linked_seats\":[]},{\"place\":\"14\",\"row\":\"11\",\"x_coord\":835,\"y_coord\":231,\"linked_seats\":[]},{\"place\":\"15\",\"row\":\"11\",\"x_coord\":815,\"y_coord\":225,\"linked_seats\":[]},{\"place\":\"16\",\"row\":\"11\",\"x_coord\":795,\"y_coord\":221,\"linked_seats\":[]},{\"place\":\"17\",\"row\":\"11\",\"x_coord\":775,\"y_coord\":216,\"linked_seats\":[]},{\"place\":\"18\",\"row\":\"11\",\"x_coord\":755,\"y_coord\":213,\"linked_seats\":[]},{\"place\":\"19\",\"row\":\"11\",\"x_coord\":734,\"y_coord\":210,\"linked_seats\":[]},{\"place\":\"20\",\"row\":\"11\",\"x_coord\":714,\"y_coord\":207,\"linked_seats\":[]},{\"place\":\"21\",\"row\":\"11\",\"x_coord\":693,\"y_coord\":205,\"linked_seats\":[]},{\"place\":\"22\",\"row\":\"11\",\"x_coord\":673,\"y_coord\":204,\"linked_seats\":[]},{\"place\":\"23\",\"row\":\"11\",\"x_coord\":652,\"y_coord\":203,\"linked_seats\":[]},{\"place\":\"24\",\"row\":\"11\",\"x_coord\":632,\"y_coord\":203,\"linked_seats\":[]},{\"place\":\"25\",\"row\":\"11\",\"x_coord\":611,\"y_coord\":203,\"linked_seats\":[]},{\"place\":\"26\",\"row\":\"11\",\"x_coord\":590,\"y_coord\":204,\"linked_seats\":[]},{\"place\":\"27\",\"row\":\"11\",\"x_coord\":570,\"y_coord\":205,\"linked_seats\":[]},{\"place\":\"28\",\"row\":\"11\",\"x_coord\":549,\"y_coord\":207,\"linked_seats\":[]},{\"place\":\"29\",\"row\":\"11\",\"x_coord\":529,\"y_coord\":209,\"linked_seats\":[]},{\"place\":\"30\",\"row\":\"11\",\"x_coord\":508,\"y_coord\":213,\"linked_seats\":[]},{\"place\":\"31\",\"row\":\"11\",\"x_coord\":488,\"y_coord\":216,\"linked_seats\":[]},{\"place\":\"32\",\"row\":\"11\",\"x_coord\":468,\"y_coord\":220,\"linked_seats\":[]},{\"place\":\"33\",\"row\":\"11\",\"x_coord\":448,\"y_coord\":225,\"linked_seats\":[]},{\"place\":\"34\",\"row\":\"11\",\"x_coord\":428,\"y_coord\":230,\"linked_seats\":[]},{\"place\":\"35\",\"row\":\"11\",\"x_coord\":371,\"y_coord\":248,\"linked_seats\":[]},{\"place\":\"36\",\"row\":\"11\",\"x_coord\":353,\"y_coord\":255,\"linked_seats\":[]},{\"place\":\"37\",\"row\":\"11\",\"x_coord\":335,\"y_coord\":263,\"linked_seats\":[]},{\"place\":\"38\",\"row\":\"11\",\"x_coord\":316,\"y_coord\":271,\"linked_seats\":[]},{\"place\":\"39\",\"row\":\"11\",\"x_coord\":299,\"y_coord\":279,\"linked_seats\":[]},{\"place\":\"40\",\"row\":\"11\",\"x_coord\":281,\"y_coord\":288,\"linked_seats\":[]},{\"place\":\"41\",\"row\":\"11\",\"x_coord\":263,\"y_coord\":297,\"linked_seats\":[]},{\"place\":\"42\",\"row\":\"11\",\"x_coord\":246,\"y_coord\":307,\"linked_seats\":[]},{\"place\":\"43\",\"row\":\"11\",\"x_coord\":229,\"y_coord\":318,\"linked_seats\":[]},{\"place\":\"44\",\"row\":\"11\",\"x_coord\":213,\"y_coord\":328,\"linked_seats\":[]},{\"place\":\"45\",\"row\":\"11\",\"x_coord\":196,\"y_coord\":340,\"linked_seats\":[]},{\"place\":\"46\",\"row\":\"11\",\"x_coord\":180,\"y_coord\":351,\"linked_seats\":[]},{\"place\":\"47\",\"row\":\"11\",\"x_coord\":164,\"y_coord\":363,\"linked_seats\":[]},{\"place\":\"1\",\"row\":\"12\",\"x_coord\":1093,\"y_coord\":332,\"linked_seats\":[]},{\"place\":\"2\",\"row\":\"12\",\"x_coord\":1076,\"y_coord\":320,\"linked_seats\":[]},{\"place\":\"3\",\"row\":\"12\",\"x_coord\":1060,\"y_coord\":309,\"linked_seats\":[]},{\"place\":\"4\",\"row\":\"12\",\"x_coord\":1043,\"y_coord\":298,\"linked_seats\":[]},{\"place\":\"5\",\"row\":\"12\",\"x_coord\":1025,\"y_coord\":288,\"linked_seats\":[]},{\"place\":\"6\",\"row\":\"12\",\"x_coord\":1008,\"y_coord\":278,\"linked_seats\":[]},{\"place\":\"7\",\"row\":\"12\",\"x_coord\":990,\"y_coord\":268,\"linked_seats\":[]},{\"place\":\"8\",\"row\":\"12\",\"x_coord\":972,\"y_coord\":259,\"linked_seats\":[]},{\"place\":\"9\",\"row\":\"12\",\"x_coord\":954,\"y_coord\":250,\"linked_seats\":[]},{\"place\":\"10\",\"row\":\"12\",\"x_coord\":935,\"y_coord\":242,\"linked_seats\":[]},{\"place\":\"11\",\"row\":\"12\",\"x_coord\":916,\"y_coord\":235,\"linked_seats\":[]},{\"place\":\"12\",\"row\":\"12\",\"x_coord\":897,\"y_coord\":227,\"linked_seats\":[]},{\"place\":\"13\",\"row\":\"12\",\"x_coord\":842,\"y_coord\":209,\"linked_seats\":[]},{\"place\":\"14\",\"row\":\"12\",\"x_coord\":822,\"y_coord\":204,\"linked_seats\":[]},{\"place\":\"15\",\"row\":\"12\",\"x_coord\":802,\"y_coord\":200,\"linked_seats\":[]},{\"place\":\"16\",\"row\":\"12\",\"x_coord\":782,\"y_coord\":195,\"linked_seats\":[]},{\"place\":\"17\",\"row\":\"12\",\"x_coord\":762,\"y_coord\":192,\"linked_seats\":[]},{\"place\":\"18\",\"row\":\"12\",\"x_coord\":742,\"y_coord\":189,\"linked_seats\":[]},{\"place\":\"19\",\"row\":\"12\",\"x_coord\":722,\"y_coord\":186,\"linked_seats\":[]},{\"place\":\"20\",\"row\":\"12\",\"x_coord\":702,\"y_coord\":184,\"linked_seats\":[]},{\"place\":\"21\",\"row\":\"12\",\"x_coord\":681,\"y_coord\":182,\"linked_seats\":[]},{\"place\":\"22\",\"row\":\"12\",\"x_coord\":661,\"y_coord\":181,\"linked_seats\":[]},{\"place\":\"23\",\"row\":\"12\",\"x_coord\":641,\"y_coord\":181,\"linked_seats\":[]},{\"place\":\"24\",\"row\":\"12\",\"x_coord\":621,\"y_coord\":181,\"linked_seats\":[]},{\"place\":\"25\",\"row\":\"12\",\"x_coord\":600,\"y_coord\":181,\"linked_seats\":[]},{\"place\":\"26\",\"row\":\"12\",\"x_coord\":580,\"y_coord\":182,\"linked_seats\":[]},{\"place\":\"27\",\"row\":\"12\",\"x_coord\":560,\"y_coord\":184,\"linked_seats\":[]},{\"place\":\"28\",\"row\":\"12\",\"x_coord\":539,\"y_coord\":186,\"linked_seats\":[]},{\"place\":\"29\",\"row\":\"12\",\"x_coord\":519,\"y_coord\":189,\"linked_seats\":[]},{\"place\":\"30\",\"row\":\"12\",\"x_coord\":499,\"y_coord\":192,\"linked_seats\":[]},{\"place\":\"31\",\"row\":\"12\",\"x_coord\":479,\"y_coord\":195,\"linked_seats\":[]},{\"place\":\"32\",\"row\":\"12\",\"x_coord\":459,\"y_coord\":200,\"linked_seats\":[]},{\"place\":\"33\",\"row\":\"12\",\"x_coord\":439,\"y_coord\":204,\"linked_seats\":[]},{\"place\":\"34\",\"row\":\"12\",\"x_coord\":420,\"y_coord\":210,\"linked_seats\":[]},{\"place\":\"35\",\"row\":\"12\",\"x_coord\":364,\"y_coord\":228,\"linked_seats\":[]},{\"place\":\"36\",\"row\":\"12\",\"x_coord\":345,\"y_coord\":235,\"linked_seats\":[]},{\"place\":\"37\",\"row\":\"12\",\"x_coord\":326,\"y_coord\":242,\"linked_seats\":[]},{\"place\":\"38\",\"row\":\"12\",\"x_coord\":308,\"y_coord\":251,\"linked_seats\":[]},{\"place\":\"39\",\"row\":\"12\",\"x_coord\":289,\"y_coord\":259,\"linked_seats\":[]},{\"place\":\"40\",\"row\":\"12\",\"x_coord\":271,\"y_coord\":268,\"linked_seats\":[]},{\"place\":\"41\",\"row\":\"12\",\"x_coord\":254,\"y_coord\":278,\"linked_seats\":[]},{\"place\":\"42\",\"row\":\"12\",\"x_coord\":236,\"y_coord\":288,\"linked_seats\":[]},{\"place\":\"43\",\"row\":\"12\",\"x_coord\":219,\"y_coord\":298,\"linked_seats\":[]},{\"place\":\"44\",\"row\":\"12\",\"x_coord\":202,\"y_coord\":309,\"linked_seats\":[]},{\"place\":\"45\",\"row\":\"12\",\"x_coord\":185,\"y_coord\":321,\"linked_seats\":[]},{\"place\":\"46\",\"row\":\"12\",\"x_coord\":168,\"y_coord\":332,\"linked_seats\":[]},{\"place\":\"1\",\"row\":\"13\",\"x_coord\":1051,\"y_coord\":277,\"linked_seats\":[]},{\"place\":\"2\",\"row\":\"13\",\"x_coord\":1033,\"y_coord\":267,\"linked_seats\":[]},{\"place\":\"3\",\"row\":\"13\",\"x_coord\":1016,\"y_coord\":257,\"linked_seats\":[]},{\"place\":\"4\",\"row\":\"13\",\"x_coord\":998,\"y_coord\":247,\"linked_seats\":[]},{\"place\":\"5\",\"row\":\"13\",\"x_coord\":980,\"y_coord\":238,\"linked_seats\":[]},{\"place\":\"6\",\"row\":\"13\",\"x_coord\":961,\"y_coord\":230,\"linked_seats\":[]},{\"place\":\"7\",\"row\":\"13\",\"x_coord\":943,\"y_coord\":222,\"linked_seats\":[]},{\"place\":\"8\",\"row\":\"13\",\"x_coord\":924,\"y_coord\":214,\"linked_seats\":[]},{\"place\":\"9\",\"row\":\"13\",\"x_coord\":905,\"y_coord\":207,\"linked_seats\":[]},{\"place\":\"10\",\"row\":\"13\",\"x_coord\":849,\"y_coord\":189,\"linked_seats\":[]},{\"place\":\"11\",\"row\":\"13\",\"x_coord\":830,\"y_coord\":184,\"linked_seats\":[]},{\"place\":\"12\",\"row\":\"13\",\"x_coord\":810,\"y_coord\":179,\"linked_seats\":[]},{\"place\":\"13\",\"row\":\"13\",\"x_coord\":790,\"y_coord\":175,\"linked_seats\":[]},{\"place\":\"14\",\"row\":\"13\",\"x_coord\":771,\"y_coord\":171,\"linked_seats\":[]},{\"place\":\"15\",\"row\":\"13\",\"x_coord\":751,\"y_coord\":168,\"linked_seats\":[]},{\"place\":\"16\",\"row\":\"13\",\"x_coord\":685,\"y_coord\":160,\"linked_seats\":[]},{\"place\":\"17\",\"row\":\"13\",\"x_coord\":664,\"y_coord\":159,\"linked_seats\":[]},{\"place\":\"18\",\"row\":\"13\",\"x_coord\":598,\"y_coord\":159,\"linked_seats\":[]},{\"place\":\"19\",\"row\":\"13\",\"x_coord\":578,\"y_coord\":160,\"linked_seats\":[]},{\"place\":\"20\",\"row\":\"13\",\"x_coord\":512,\"y_coord\":167,\"linked_seats\":[]},{\"place\":\"21\",\"row\":\"13\",\"x_coord\":492,\"y_coord\":171,\"linked_seats\":[]},{\"place\":\"22\",\"row\":\"13\",\"x_coord\":472,\"y_coord\":174,\"linked_seats\":[]},{\"place\":\"23\",\"row\":\"13\",\"x_coord\":452,\"y_coord\":179,\"linked_seats\":[]},{\"place\":\"24\",\"row\":\"13\",\"x_coord\":433,\"y_coord\":183,\"linked_seats\":[]},{\"place\":\"25\",\"row\":\"13\",\"x_coord\":413,\"y_coord\":189,\"linked_seats\":[]},{\"place\":\"26\",\"row\":\"13\",\"x_coord\":356,\"y_coord\":207,\"linked_seats\":[]},{\"place\":\"27\",\"row\":\"13\",\"x_coord\":337,\"y_coord\":214,\"linked_seats\":[]},{\"place\":\"28\",\"row\":\"13\",\"x_coord\":318,\"y_coord\":222,\"linked_seats\":[]},{\"place\":\"29\",\"row\":\"13\",\"x_coord\":300,\"y_coord\":230,\"linked_seats\":[]},{\"place\":\"30\",\"row\":\"13\",\"x_coord\":282,\"y_coord\":239,\"linked_seats\":[]},{\"place\":\"31\",\"row\":\"13\",\"x_coord\":263,\"y_coord\":248,\"linked_seats\":[]},{\"place\":\"32\",\"row\":\"13\",\"x_coord\":246,\"y_coord\":257,\"linked_seats\":[]},{\"place\":\"33\",\"row\":\"13\",\"x_coord\":228,\"y_coord\":267,\"linked_seats\":[]},{\"place\":\"34\",\"row\":\"13\",\"x_coord\":211,\"y_coord\":277,\"linked_seats\":[]}],\"outline\":\" M1159.2303466796875 278.8973846435547 C1163.4302978515625 282.16017150878906 1165.0760498046875 287.74119567871094 1163.28125 292.7469177246094 L1038.2162475585938 640.0599365234375 C1035.9697875976562 646.2984008789062 1029.0941772460938 649.5336303710938 1022.859130859375 647.2859497070312 C1020.8023071289062 646.5444946289062 1018.987060546875 645.2550048828125 1017.609375 643.5565795898438 C1012.8656005859375 637.708740234375 1008.8834838867188 632.9627075195312 1005.6630859375 629.3184204101562 C914.0103759765625 525.6034545898438 780.0014038085938 460.1969909667969 630.71630859375 460.1969909667969 C479.64404296875 460.1969909667969 344.2150115966797 527.1788330078125 252.4951629638672 633.0597534179688 C250.09230041503906 635.8336181640625 247.19119262695312 639.32080078125 243.79188537597656 643.5213012695312 C239.62135314941406 648.6748046875 232.06503295898438 649.4697875976562 226.91436767578125 645.2969970703125 C225.2158203125 643.9208984375 223.92511749267578 642.1068725585938 223.18157196044922 640.050537109375 L97.7192314863205 293.0821075439453 C95.92442631721497 288.07737731933594 97.5681636929512 282.50035095214844 101.76404571533203 279.23558044433594 C124.69233131408691 261.40187072753906 148.54302978515625 244.70278930664062 173.2411117553711 229.22137451171875 C240.14012145996094 187.2685546875 313.212890625 154.2405891418457 390.7876892089844 131.82839965820312 C466.9528503417969 109.79641628265381 547.458984375 98.0 630.71630859375 98.0 C713.97265625 98.0 794.478759765625 109.79641628265381 870.6439208984375 131.82839965820312 C948.2177124023438 154.2405891418457 1021.29150390625 187.2685546875 1088.1905517578125 229.22137451171875 C1112.728515625 244.6017303466797 1136.4351806640625 261.1907653808594 1159.2303466796875 278.8973846435547 Z\",\"sections\":[],\"admission\":false},{\"id\":3,\"name\":\"Ложа бельэтажа (левая)\",\"seats\":[{\"place\":\"1\",\"row\":\"1\",\"x_coord\":1086,\"y_coord\":619,\"linked_seats\":[]},{\"place\":\"2\",\"row\":\"1\",\"x_coord\":1094,\"y_coord\":598,\"linked_seats\":[]},{\"place\":\"3\",\"row\":\"1\",\"x_coord\":1102,\"y_coord\":577,\"linked_seats\":[]},{\"place\":\"4\",\"row\":\"1\",\"x_coord\":1122,\"y_coord\":521,\"linked_seats\":[]},{\"place\":\"5\",\"row\":\"1\",\"x_coord\":1129,\"y_coord\":501,\"linked_seats\":[]},{\"place\":\"6\",\"row\":\"1\",\"x_coord\":1136,\"y_coord\":481,\"linked_seats\":[]},{\"place\":\"7\",\"row\":\"1\",\"x_coord\":1143,\"y_coord\":461,\"linked_seats\":[]}],\"outline\":\" M1200.2718505859375 413.2803077697754 L1111.3533172607422 657.1205139160156 C1109.1448059082031 663.177978515625 1102.5392417907715 666.4009399414062 1096.4059295654297 664.4140625 L1048.2919359207153 648.8275146484375 C1041.997879266739 646.7887268066406 1038.5473302602768 640.0323181152344 1040.5861095190048 633.7372131347656 C1040.6270447969437 633.6114044189453 1040.6699770092964 633.4846038818359 1040.7159044742584 633.3598022460938 L1130.088722229004 385.91427087783813 C1132.336166381836 379.69104075431824 1139.2033233642578 376.4681005477905 1145.4264907836914 378.7155721783638 C1145.5632781982422 378.7644953727722 1145.6980590820312 378.81641387939453 1145.8328475952148 378.8703292608261 L1193.4915618896484 398.06120109558105 C1199.486083984375 400.4754104614258 1202.486343383789 407.2088394165039 1200.2718505859375 413.2803077697754 Z\",\"sections\":[],\"admission\":false},{\"id\":4,\"name\":\"Ложа бельэтажа (правая)\",\"seats\":[{\"place\":\"1\",\"row\":\"1\",\"x_coord\":175,\"y_coord\":619,\"linked_seats\":[]},{\"place\":\"2\",\"row\":\"1\",\"x_coord\":167,\"y_coord\":598,\"linked_seats\":[]},{\"place\":\"3\",\"row\":\"1\",\"x_coord\":159,\"y_coord\":577,\"linked_seats\":[]},{\"place\":\"4\",\"row\":\"1\",\"x_coord\":139,\"y_coord\":521,\"linked_seats\":[]},{\"place\":\"5\",\"row\":\"1\",\"x_coord\":132,\"y_coord\":501,\"linked_seats\":[]},{\"place\":\"6\",\"row\":\"1\",\"x_coord\":125,\"y_coord\":481,\"linked_seats\":[]},{\"place\":\"7\",\"row\":\"1\",\"x_coord\":118,\"y_coord\":461,\"linked_seats\":[]}],\"outline\":\" M60.7140948176384 413.24547576904297 L148.6649627685547 657.0821228027344 C150.85747528076172 663.1621398925781 157.4739227294922 666.4053344726562 163.6193389892578 664.4142761230469 L211.7128448486328 648.8253173828125 C218.0039520263672 646.7853393554688 221.45188903808594 640.0293273925781 219.4140625 633.7336273193359 C219.37713623046875 633.6197967529297 219.33822631835938 633.5049743652344 219.29830932617188 633.3921356201172 L130.88937377929688 385.95281076431274 C128.66293334960938 379.7210202217102 121.80996704101562 376.47481763362885 115.58072280883789 378.7025254368782 C115.43302536010742 378.7554472088814 115.28632736206055 378.8123631477356 115.1396255493164 378.8712760210037 L67.50518608093262 398.0629138946533 C61.5264310836792 400.4713554382324 58.52657496929169 407.1804389953613 60.7140948176384 413.24547576904297 Z\",\"sections\":[],\"admission\":false},{\"id\":5,\"name\":\"Ложа бенуара (правая)\",\"seats\":[{\"place\":\"6\",\"row\":\"1\",\"x_coord\":194,\"y_coord\":174,\"linked_seats\":[]},{\"place\":\"5\",\"row\":\"1\",\"x_coord\":212,\"y_coord\":164,\"linked_seats\":[]},{\"place\":\"4\",\"row\":\"1\",\"x_coord\":230,\"y_coord\":155,\"linked_seats\":[]},{\"place\":\"3\",\"row\":\"1\",\"x_coord\":285,\"y_coord\":130,\"linked_seats\":[]},{\"place\":\"2\",\"row\":\"1\",\"x_coord\":304,\"y_coord\":122,\"linked_seats\":[]},{\"place\":\"1\",\"row\":\"1\",\"x_coord\":323,\"y_coord\":115,\"linked_seats\":[]}],\"outline\":\" M378.8134765625 136.0311279296875 C310.2746124267578 156.8697967529297 245.36202239990234 186.0309600830078 185.2545280456543 222.32298278808594 C179.00691986083984 226.0955047607422 170.87324142456055 223.24215698242188 168.40976333618164 216.37777709960938 L142.6770924925804 144.66400909423828 C140.79701614379883 139.4273910522461 142.94182163476944 133.6079330444336 147.75189971923828 130.80748748779297 C209.97423553466797 94.58034133911133 276.64501953125 65.14372444152832 346.74928283691406 43.516618490219116 C352.6492462158203 41.697227001190186 358.94081115722656 44.828017473220825 361.02467346191406 50.6345009803772 L386.32080078125 121.13367462158203 C388.5445251464844 127.33138275146484 385.11802673339844 134.11392974853516 378.8134765625 136.0311279296875 Z\",\"sections\":[],\"admission\":false},{\"id\":6,\"name\":\"Ложа бенуара А, Б\",\"seats\":[{\"place\":\"16\",\"row\":\"1\",\"x_coord\":438,\"y_coord\":81,\"linked_seats\":[]},{\"place\":\"15\",\"row\":\"1\",\"x_coord\":459,\"y_coord\":77,\"linked_seats\":[]},{\"place\":\"14\",\"row\":\"1\",\"x_coord\":479,\"y_coord\":73,\"linked_seats\":[]},{\"place\":\"13\",\"row\":\"1\",\"x_coord\":499,\"y_coord\":70,\"linked_seats\":[]},{\"place\":\"12\",\"row\":\"1\",\"x_coord\":559,\"y_coord\":64,\"linked_seats\":[]},{\"place\":\"11\",\"row\":\"1\",\"x_coord\":579,\"y_coord\":62,\"linked_seats\":[]},{\"place\":\"10\",\"row\":\"1\",\"x_coord\":600,\"y_coord\":61,\"linked_seats\":[]},{\"place\":\"9\",\"row\":\"1\",\"x_coord\":621,\"y_coord\":61,\"linked_seats\":[]},{\"place\":\"8\",\"row\":\"1\",\"x_coord\":641,\"y_coord\":61,\"linked_seats\":[]},{\"place\":\"7\",\"row\":\"1\",\"x_coord\":662,\"y_coord\":61,\"linked_seats\":[]},{\"place\":\"6\",\"row\":\"1\",\"x_coord\":682,\"y_coord\":62,\"linked_seats\":[]},{\"place\":\"5\",\"row\":\"1\",\"x_coord\":703,\"y_coord\":64,\"linked_seats\":[]},{\"place\":\"4\",\"row\":\"1\",\"x_coord\":762,\"y_coord\":70,\"linked_seats\":[]},{\"place\":\"3\",\"row\":\"1\",\"x_coord\":783,\"y_coord\":73,\"linked_seats\":[]},{\"place\":\"2\",\"row\":\"1\",\"x_coord\":803,\"y_coord\":77,\"linked_seats\":[]},{\"place\":\"1\",\"row\":\"1\",\"x_coord\":823,\"y_coord\":81,\"linked_seats\":[]}],\"outline\":\" M899.3189086914062 51.80840301513672 L873.9591064453125 122.3785629272461 C871.9220275878906 128.04344940185547 865.8558349609375 131.18362426757812 860.0396728515625 129.5836181640625 C786.9583740234375 109.48369598388672 709.9829711914062 98.75642395019531 630.49951171875 98.75642395019531 C551.0170288085938 98.75642395019531 474.04161834716797 109.48369598388672 400.9603385925293 129.5836181640625 C395.14415740966797 131.18362426757812 389.0769691467285 128.04344940185547 387.04090690612793 122.3785629272461 L361.681115090847 51.80840301513672 C359.4240447282791 45.52804946899414 362.9741554260254 38.648193359375 369.41135597229004 36.837703704833984 C452.42394256591797 13.491874694824219 539.9956817626953 1.0 630.49951171875 1.0 C721.0033264160156 1.0 808.5760498046875 13.491874694824219 891.588623046875 36.837703704833984 C898.0258178710938 38.648193359375 901.575927734375 45.52804946899414 899.3189086914062 51.80840301513672 Z\",\"sections\":[],\"admission\":false},{\"id\":7,\"name\":\"Ложа бенуара (левая)\",\"seats\":[{\"place\":\"6\",\"row\":\"1\",\"x_coord\":939,\"y_coord\":115,\"linked_seats\":[]},{\"place\":\"5\",\"row\":\"1\",\"x_coord\":958,\"y_coord\":122,\"linked_seats\":[]},{\"place\":\"4\",\"row\":\"1\",\"x_coord\":977,\"y_coord\":130,\"linked_seats\":[]},{\"place\":\"3\",\"row\":\"1\",\"x_coord\":1032,\"y_coord\":155,\"linked_seats\":[]},{\"place\":\"2\",\"row\":\"1\",\"x_coord\":1050,\"y_coord\":164,\"linked_seats\":[]},{\"place\":\"1\",\"row\":\"1\",\"x_coord\":1068,\"y_coord\":174,\"linked_seats\":[]}],\"outline\":\" M1118.3229064941406 144.66400909423828 L1092.5902252197266 216.37777709960938 C1090.1267395019531 223.24215698242188 1081.9930725097656 226.0955047607422 1075.7454528808594 222.32298278808594 C1015.6369323730469 186.0309600830078 950.7253265380859 156.8697967529297 882.1864242553711 136.0311279296875 C875.882871389389 134.11392974853516 872.4553769826889 127.33138275146484 874.6791025400162 121.13367462158203 L899.9752292633057 50.6345009803772 C902.0590991973877 44.828017473220825 908.3506622314453 41.697227001190186 914.2506294250488 43.516618490219116 C984.3559265136719 65.14372444152832 1051.0257415771484 94.58034133911133 1113.2480926513672 130.80748748779297 C1118.0581817626953 133.6079330444336 1120.2029876708984 139.4273910522461 1118.3229064941406 144.66400909423828 Z\",\"sections\":[],\"admission\":false}]}"}